Workbook

Sheet Growth
B2: Aura Systems - Software Department
B3: Income Budget based on Growth
B4: Financial Numbers in EGP
M5: collection & expected | P5: Pricing Structure
B6: Growth Method | C6: 2015 | D6: 2016 | E6: 2017 | F6: 2018 | G6: 2019 | H6: 2020 | I6: 2021 | J6: 2022 | K6: 2023 | L6: 2024 | M6: 2025 | N6: 2026 | P6: 2022 | Q6: 2023 | R6: 2024 | S6: % | T6: 2025 | U6: %2 | V6: 2026 | W6: %3
B7: Products | C7: =SUM('[1]Income 2015'!$F$17:$Q$17) -> 0 | D7: =SUM('[2]Income 2016'!$F$17:$Q$17) -> 0 | E7: =SUM('[3]Income 2017'!$F$17:$Q$17) -> 37100 | F7: =SUM('[4]Income 2018'!$F$17:$Q$17) -> 117830 | G7: =SUM('[5]Income 2019'!$F$18:$Q$18) -> 12500 | H7: 30000 | I7: 34200 | J7: 40000 | K7: 0 | L7: =SUM([6]Total!$R$21:$R$22) -> 0 | M7: =SUM([7]Total!$M$21:$Q$22) -> 2140293.1 | N7: 2000000 | P7: 575 | Q7: 625 | R7: 800 | S7: =R7/Q7 -> 1.28 | T7: 1100 | U7: =Table5[[#This Row],[2025]]/Table5[[#This Row],[2024]] -> 1.375 | V7: 1250 | W7: =Table5[[#This Row],[2026]]/Table5[[#This Row],[2025]] -> 1.1363636
B8: PHP | C8: =SUM('[1]Income 2015'!$F$13:$Q$13) -> 185600 | D8: =SUM('[2]Income 2016'!$F$13:$Q$13) -> 447256 | E8: =SUM('[3]Income 2017'!$F$13:$Q$13) -> 307494 | F8: =SUM('[4]Income 2018'!$F$13:$Q$13) -> 966268.38 | G8: =SUM('[5]Income 2019'!$F$22:$Q$22) -> 826638.18 | H8: 1100000 | I8: =-1280000+2497000+300000 -> 1517000 | J8: =1630000*0.65+46000+50000+70000 -> 1225500 | K8: =1456884*12/10 -> 1748260.8 | L8: =SUM([6]Total!$R$6:$R$7) -> 2649665.9 | M8: =SUM([7]Total!$F$6:$P$7)*12/11 -> 3678723.6 | N8: 4700000 | P8: 575 | Q8: 625 | R8: 800 | S8: =R8/Q8 -> 1.28 | T8: 975 | U8: =Table5[[#This Row],[2025]]/Table5[[#This Row],[2024]] -> 1.21875 | V8: 1150 | W8: =Table5[[#This Row],[2026]]/Table5[[#This Row],[2025]] -> 1.1794872
B9: .NET | L9: =SUM([6]Total!$R$26:$R$27) -> 2799353.7 | M9: =SUM([7]Total!$F$26:$P$27)*12/11 -> 3514572.5 | N9: 4400000 | P9: 525 | Q9: 575 | R9: 800 | S9: =R9/Q9 -> 1.3913043 | T9: 975 | U9: =Table5[[#This Row],[2025]]/Table5[[#This Row],[2024]] -> 1.21875 | V9: 1150 | W9: =Table5[[#This Row],[2026]]/Table5[[#This Row],[2025]] -> 1.1794872
B10: Mobile Development | C10: 0 | D10: =SUM('[2]Income 2016'!$F$37:$Q$37) -> 33900 | E10: =SUM('[3]Income 2017'!$F$37:$Q$37) -> 84187.25 | F10: =SUM('[4]Income 2018'!$F$37:$Q$37) -> 0 | G10: =SUM('[5]Income 2019'!$F$26:$Q$26) -> 5000 | H10: 0 | I10: =680694+300000 -> 980694 | J10: =1630000*0.4 -> 652000 | K10: =348985*12/10 -> 418782 | L10: =SUM([6]Total!$R$11:$R$12) -> 899561.66 | M10: =SUM([7]Total!$F$11:$P$12)*12/11 -> 1442787.5 | N10: 2500000 | P10: 575 | Q10: 625 | R10: 800 | S10: =R10/Q10 -> 1.28 | T10: 975 | U10: =Table5[[#This Row],[2025]]/Table5[[#This Row],[2024]] -> 1.21875 | V10: 1150 | W10: =Table5[[#This Row],[2026]]/Table5[[#This Row],[2025]] -> 1.1794872
B11: Support Contracts | C11: =SUM('[1]Income 2015'!$F$29:$Q$29) -> 0 | D11: =SUM('[2]Income 2016'!$F$29:$Q$29) -> 0 | E11: =SUM('[3]Income 2017'!$F$29:$Q$29) -> 0 | F11: =SUM('[4]Income 2018'!$F$29:$Q$29) -> 11920 | G11: =SUM('[5]Income 2019'!$F$30:$Q$30) -> 155639.87 | H11: 120000 | I11: 160020 | J11: 185595 | L11: 0 | M11: 0 | N11: 0 | P11: =(P8+P12)/2 -> 525 | Q11: =(Q8+Q12)/2 -> 587.5 | R11: =(R8+R12)/2 -> 762.5 | S11: =R11/Q11 -> 1.2978723 | T11: 0 | U11: =Table5[[#This Row],[2025]]/Table5[[#This Row],[2024]] -> 0 | V11: 0 | W11: 0
B12: Websites | C12: =SUM('[1]Income 2015'!$F$25:$Q$25) -> 12750 | D12: =SUM('[2]Income 2016'!$F$25:$Q$25) -> 61008.1 | E12: =SUM('[3]Income 2017'!$F$25:$Q$25) -> 189884.75 | F12: =SUM('[4]Income 2018'!$F$25:$Q$25) -> 278837.53 | G12: =SUM('[5]Income 2019'!$F$39:$Q$39) -> 438820.47 | H12: 505000 | I12: 468300 | J12: 325000 | K12: =372000*12/11 -> 405818.18 | L12: =SUM([6]Total!$R$16:$R$17) -> 1066495.9 | M12: =SUM([7]Total!$F$16:$P$17)*12/11 -> 694293.43 | N12: 1100000 | P12: 475 | Q12: 550 | R12: 725 | S12: =R12/Q12 -> 1.3181818 | T12: 875 | U12: =Table5[[#This Row],[2025]]/Table5[[#This Row],[2024]] -> 1.2068966 | V12: 1050 | W12: =Table5[[#This Row],[2026]]/Table5[[#This Row],[2025]] -> 1.2
B13: Design | J13: 23000 | K13: 75000 | L13: =SUM([6]Total!$R$30:$R$31) -> 100918.11 | M13: =SUM([7]Total!$F$31:$P$32)*12/11 -> 314078.48 | N13: 400000 | Q13: 550 | R13: 725 | S13: =R13/Q13 -> 1.3181818 | T13: 875 | U13: =Table5[[#This Row],[2025]]/Table5[[#This Row],[2024]] -> 1.2068966 | V13: 1050 | W13: =Table5[[#This Row],[2026]]/Table5[[#This Row],[2025]] -> 1.2
B14: Hosting | C14: 0 | D14: 0 | E14: 0 | F14: 0 | G14: =SUM('[5]Income 2019'!$F$43:$Q$43) -> 62052.335 | H14: 45000 | I14: 80107 | J14: 124000 | K14: 406043 | L14: =SUM([6]Total!$R$36:$R$37) -> 373282.56 | M14: =SUM([7]Total!$F$36:$P$37)*12/11 -> 376829.19 | N14: 362000 | P14: =120*P15*1.05*1.14 -> 2243.6568 | Q14: =120*Q15*1.05*1.14 -> 3418.632 | R14: =120*R15*1.05*1.14 -> 4444.2216 | S14: =R14/Q14 -> 1.3 | T14: =150*T15*1.05*1.14 -> 8797.95 | U14: =Table5[[#This Row],[2025]]/Table5[[#This Row],[2024]] -> 1.979638 | V14: =150*V15*1.05*1.14 -> 8456.805 | W14: =Table5[[#This Row],[2026]]/Table5[[#This Row],[2025]] -> 0.96122449
B15: Total | C15: =SUM(C7:C14) -> 198350 | D15: =SUM(D7:D14) -> 542164.1 | E15: =SUM(E7:E14) -> 618666 | F15: =SUM(F7:F14) -> 1374855.9 | G15: =SUM(G7:G14) -> 1500650.9 | H15: =SUM(H7:H14) -> 1800000 | I15: =SUM(I7:I14) -> 3240321 | J15: =SUM(J7:J14) -> 2575095 | ... N15: =SUM(N7:N14) -> 15462000 | P15: 15.62 | Q15: 23.8 | R15: 30.94 | S15: =R15/Q15 -> 1.3 | T15: 49 | U15: =Table5[[#This Row],[2025]]/Table5[[#This Row],[2024]] -> 1.5837104 | V15: 47.1 | W15: =Table5[[#This Row],[2026]]/Table5[[#This Row],[2025]] -> 0.96122449
G16: =G15/F15 -> 1.0914968 | H16: =H15/G15 -> 1.1994795 | I16: =I15/H15 -> 1.8001783 | J16: =J15/I15 -> 0.79470367 | K16: =K15/J15 -> 1.1859384 | L16: =L15/K15 -> 2.5833418 | M16: =M15/L15 -> 1.5415324 | N16: =N15/M15 -> 1.2713811

Sheet Activity
B2: Aura Systems - Software Department
B3: Income Budget based on Activities
B4: Financial Numbers in EGP
B6: VAT Rate | C6: 0.14
B8: 0. Summary
B9: Activity Method
B10: Activity | C10: Total | D10: 2023 | E10: Growth
B11: Support Contracts | C11: =O61 -> 362178 | D11: 400000 | E11: =Table12[[#This Row],[Total]]/Table12[[#This Row],[2023]]-1 -> -0.094555
B12: Custom Development | C12: =O108 -> 2664180 | D12: =Growth!K8 -> 1748260.8 | E12: =Table12[[#This Row],[Total]]/Table12[[#This Row],[2023]]-1 -> 0.52390307
B13: Products | C13: =O117 -> 123120 | D13: =Growth!K7 -> 0 | E13: =Table12[[#This Row],[Total]]/Table12[[#This Row],[2023]]-1 -> #DIV/0!
B14: Websites | C14: =O136 -> 873840 | D14: =Growth!K12 -> 405818.18 | E14: =Table12[[#This Row],[Total]]/Table12[[#This Row],[2023]]-1 -> 1.1532796
B15: Hosting | C15: =O149 -> 215070 | D15: =Growth!K14 -> 406043 | E15: =Table12[[#This Row],[Total]]/Table12[[#This Row],[2023]]-1 -> -0.47032703
B16: Mobile Development | C16: =O184 -> 1207260 | D16: =Growth!K10 -> 418782 | E16: =Table12[[#This Row],[Total]]/Table12[[#This Row],[2023]]-1 -> 1.8827887
B17: Design | C17: =[8]!Table2[[#Totals],[Total]] -> #REF! | D17: =Growth!K13 -> 75000 | E17: =Table12[[#This Row],[Total]]/Table12[[#This Row],[2023]]-1 -> #REF!
B18: .NET | C18: =[8]!Table2[[#Totals],[Total]] -> #REF! | D18: =Growth!K9 -> 0 | E18: =Table12[[#This Row],[Total]]/Table12[[#This Row],[2023]]-1 -> #REF!
C19: =SUBTOTAL(109,Table12[Total]) -> #REF! | D19: =SUBTOTAL(109,Table12[2023]) -> 3453904 | E19: =Table12[[#Totals],[Total]]/Table12[[#Totals],[2023]] -> #REF!
B21: 1. Support Contracts
B22: Support Retainer Pricing
C23: Value
B24: iScore SME | C24: =2.5*3000*1.14 -> 8550
B25: iScore ECR | C25: =2.5*3000*1.14 -> 8550
B26: Smart Furniture | C26: =3500*1.14 -> 3990
B27: Cheers | C27: =3500*1.14 -> 3990
B28: I Make This | C28: =2600*1.14 -> 2964
B29: EEP Hayah | C29: =1500*1.14 -> 1710
B30: Spoon | C30: =1000*1.14 -> 1140
B35: Support Retainer Contracts
C36: 44927 | D36: 44958 | E36: 44986 | F36: 45017 | G36: 45047 | H36: 45078 | I36: 45108 | J36: 45139 | K36: 44805 | L36: 45200 | M36: 45231 | N36: 45261 | O36: Total
B37: =B24 -> iScore SME | C37: 1 | D37: 1 | E37: 1 | F37: 1 | G37: 1 | H37: 1 | I37: 1 | J37: 1 | K37: 1 | L37: 1 | M37: 1 | N37: 1 | O37: =SUM(C37:N37) -> 12
B38: =B25 -> iScore ECR | C38: 1 | D38: 1 | E38: 1 | F38: 1 | G38: 1 | H38: 1 | I38: 1 | J38: 1 | K38: 1 | L38: 1 | M38: 1 | N38: 1 | O38: =SUM(C38:N38) -> 12
B39: =B26 -> Smart Furniture | C39: 1 | D39: 1 | E39: 1 | F39: 1 | G39: 1 | H39: 1 | I39: 1 | J39: 1 | K39: 1 | L39: 1 | M39: 1 | N39: 1 | O39: =SUM(C39:N39) -> 12
B40: =B27 -> Cheers | C40: 1 | D40: 1 | E40: 1 | F40: 1 | G40: 1 | H40: 1 | I40: 1 | J40: 1 | K40: 1 | L40: 1 | M40: 1 | N40: 1 | O40: =SUM(C40:N40) -> 12
B41: =B28 -> I Make This | C41: 1 | D41: 1 | E41: 1 | F41: 1 | G41: 1 | H41: 1 | I41: 1 | J41: 1 | K41: 1 | L41: 1 | M41: 1 | N41: 1 | O41: =SUM(C41:N41) -> 12
B42: =B29 -> EEP Hayah | C42: 1 | D42: 1 | E42: 1 | F42: 0 | G42: 0 | H42: 0 | I42: 0 | J42: 1 | K42: 1 | L42: 1 | M42: 1 | N42: 0 | O42: =SUM(C42:N42) -> 7
B43: =B30 -> Spoon | C43: 1 | D43: 1 | E43: 1 | F43: 1 | G43: 1 | H43: 1 | I43: 1 | J43: 1 | K43: 1 | L43: 1 | M43: 1 | N43: 1 | O43: =SUM(C43:N43) -> 12
B44: =B31 -> 0 | O44: =SUM(C44:N44) -> 0
B45: =B32 -> 0 | O45: =SUM(C45:N45) -> 0
B46: =B33 -> 0 | O46: =SUM(C46:N46) -> 0
B47: Total Retainer Contracts | C47: =SUM(C37:C46) -> 7 | D47: =SUM(D37:D46) -> 7 | E47: =SUM(E37:E46) -> 7 | F47: =SUM(F37:F46) -> 6 | G47: =SUM(G37:G46) -> 6 | H47: =SUM(H37:H46) -> 6 | I47: =SUM(I37:I46) -> 6 | J47: =SUM(J37:J46) -> 7 | ... O47: =SUM(O37:O46) -> 79
B49: Support Retainer Sales
C50: 44927 | D50: 44958 | E50: 44986 | F50: 45017 | G50: 45047 | H50: 45078 | I50: 45108 | J50: 45139 | K50: 44805 | L50: 45200 | M50: 45231 | N50: 45261 | O50: Total
B51: =B37 -> iScore SME | C51: =C37*$C24 -> 8550 | D51: =D37*$C24 -> 8550 | E51: =E37*$C24 -> 8550 | F51: =F37*$C24 -> 8550 | G51: =G37*$C24 -> 8550 | H51: =H37*$C24 -> 8550 | I51: =I37*$C24 -> 8550 | J51: =J37*$C24 -> 8550 | ... N51: =N37*$C24 -> 8550 | O51: =SUM(C51:N51) -> 102600
B52: =B38 -> iScore ECR | C52: =C38*$C25 -> 8550 | D52: =D38*$C25 -> 8550 | E52: =E38*$C25 -> 8550 | F52: =F38*$C25 -> 8550 | G52: =G38*$C25 -> 8550 | H52: =H38*$C25 -> 8550 | I52: =I38*$C25 -> 8550 | J52: =J38*$C25 -> 8550 | ... N52: =N38*$C25 -> 8550 | O52: =SUM(C52:N52) -> 102600
B53: =B39 -> Smart Furniture | C53: =C39*$C26 -> 3990 | D53: =D39*$C26 -> 3990 | E53: =E39*$C26 -> 3990 | F53: =F39*$C26 -> 3990 | G53: =G39*$C26 -> 3990 | H53: =H39*$C26 -> 3990 | I53: =I39*$C26 -> 3990 | J53: =J39*$C26 -> 3990 | ... N53: =N39*$C26 -> 3990 | O53: =SUM(C53:N53) -> 47880
B54: =B40 -> Cheers | C54: =C40*$C27 -> 3990 | D54: =D40*$C27 -> 3990 | E54: =E40*$C27 -> 3990 | F54: =F40*$C27 -> 3990 | G54: =G40*$C27 -> 3990 | H54: =H40*$C27 -> 3990 | I54: =I40*$C27 -> 3990 | J54: =J40*$C27 -> 3990 | ... N54: =N40*$C27 -> 3990 | O54: =SUM(C54:N54) -> 47880
B55: =B41 -> I Make This | C55: =C41*$C28 -> 2964 | D55: =D41*$C28 -> 2964 | E55: =E41*$C28 -> 2964 | F55: =F41*$C28 -> 2964 | G55: =G41*$C28 -> 2964 | H55: =H41*$C28 -> 2964 | I55: =I41*$C28 -> 2964 | J55: =J41*$C28 -> 2964 | ... N55: =N41*$C28 -> 2964 | O55: =SUM(C55:N55) -> 35568
B56: =B42 -> EEP Hayah | C56: =C42*$C29 -> 1710 | D56: =D42*$C29 -> 1710 | E56: =E42*$C29 -> 1710 | F56: =F42*$C29 -> 0 | G56: =G42*$C29 -> 0 | H56: =H42*$C29 -> 0 | I56: =I42*$C29 -> 0 | J56: =J42*$C29 -> 1710 | ... N56: =N42*$C29 -> 0 | O56: =SUM(C56:N56) -> 11970
B57: =B43 -> Spoon | C57: =C43*$C30 -> 1140 | D57: =D43*$C30 -> 1140 | E57: =E43*$C30 -> 1140 | F57: =F43*$C30 -> 1140 | G57: =G43*$C30 -> 1140 | H57: =H43*$C30 -> 1140 | I57: =I43*$C30 -> 1140 | J57: =J43*$C30 -> 1140 | ... N57: =N43*$C30 -> 1140 | O57: =SUM(C57:N57) -> 13680
B58: =B44 -> 0 | C58: =C44*$C31 -> 0 | D58: =D44*$C31 -> 0 | E58: =E44*$C31 -> 0 | F58: =F44*$C31 -> 0 | G58: =G44*$C31 -> 0 | H58: =H44*$C31 -> 0 | I58: =I44*$C31 -> 0 | J58: =J44*$C31 -> 0 | ... N58: =N44*$C31 -> 0 | O58: =SUM(C58:N58) -> 0
B59: =B45 -> 0 | C59: =C45*$C32 -> 0 | D59: =D45*$C32 -> 0 | E59: =E45*$C32 -> 0 | F59: =F45*$C32 -> 0 | G59: =G45*$C32 -> 0 | H59: =H45*$C32 -> 0 | I59: =I45*$C32 -> 0 | J59: =J45*$C32 -> 0 | ... N59: =N45*$C32 -> 0 | O59: =SUM(C59:N59) -> 0
B60: =B46 -> 0 | C60: =C46*$C33 -> 0 | D60: =D46*$C33 -> 0 | E60: =E46*$C33 -> 0 | F60: =F46*$C33 -> 0 | G60: =G46*$C33 -> 0 | H60: =H46*$C33 -> 0 | I60: =I46*$C33 -> 0 | J60: =J46*$C33 -> 0 | ... N60: =N46*$C33 -> 0 | O60: =SUM(C60:N60) -> 0
B61: Total Retainer Contracts Sales | C61: =SUM(C51:C60) -> 30894 | D61: =SUM(D51:D60) -> 30894 | E61: =SUM(E51:E60) -> 30894 | F61: =SUM(F51:F60) -> 29184 | G61: =SUM(G51:G60) -> 29184 | H61: =SUM(H51:H60) -> 29184 | I61: =SUM(I51:I60) -> 29184 | J61: =SUM(J51:J60) -> 30894 | ... O61: =SUM(O51:O60) -> 362178
B63: 2. Custom Development
B64: Development Month Pricing | C64: =600*95*(1+C6) -> 64980
B66: Custom Development Pricing
C67: Value
B68: Alfa Electronics | C68: =540*100*1.14 -> 61560
B69: VIPFirst | C69: =5000*30*1.14 -> 171000
B70: Project 1 | C70: =3*C64 -> 194940
B71: Project 2 | C71: =4*C64 -> 259920
B72: Project 3 | C72: =4*C64 -> 259920
B73: Project 4 | C73: =5*C64 -> 324900
B74: Project 5 | C74: =5*C64 -> 324900
B75: Project 6 | C75: =6*C64 -> 389880
B80: Custom Development Contracts
C81: 44927 | D81: 44958 | E81: 44986 | F81: 45017 | G81: 45047 | H81: 45078 | I81: 45108 | J81: 45139 | K81: 45170 | L81: 45200 | M81: 45231 | N81: 45261 | O81: Total
B82: =B68 -> Alfa Electronics | C82: 1 | D82: 1 | E82: 1 | F82: 1 | G82: 1 | H82: 1 | I82: 1 | J82: 1 | K82: 1 | L82: 1 | M82: 1 | N82: 1 | O82: =SUM(C82:N82) -> 12
B83: =B69 -> VIPFirst | C83: 0.1 | D83: 0.25 | E83: 0.25 | F83: 0.25 | G83: 0.15 | O83: =SUM(C83:N83) -> 1
B84: =B70 -> Project 1 | E84: 0.25 | F84: 0.25 | G84: 0.25 | H84: 0.15 | I84: 0.1 | O84: =SUM(E84:N84) -> 1
B85: =B71 -> Project 2 | G85: 0.3 | H85: 0.1 | I85: 0.25 | J85: 0.25 | K85: 0.1 | O85: =SUM(G85:N85) -> 1
B86: =B72 -> Project 3 | F86: 0.3 | G86: 0.1 | J86: 0.25 | L86: 0.25 | N86: 0.1 | O86: =SUM(F86:N86) -> 1
B87: =B73 -> Project 4 | I87: 0.3 | J87: 0.1 | K87: 0.25 | L87: 0.25 | M87: 0.1 | O87: =SUM(C87:N87) -> 1
B88: =B74 -> Project 5 | H88: 0.25 | J88: 0.25 | L88: 0.25 | N88: 0.25 | O88: =SUM(C88:N88) -> 1
B89: =B75 -> Project 6 | E89: 0.15 | F89: 0.15 | H89: 0.15 | I89: 0.15 | K89: 0.2 | M89: 0.2 | O89: =SUM(C89:N89) -> 1
B90: =B76 -> 0 | O90: =SUM(C90:N90) -> 0
B91: =B77 -> 0 | O91: =SUM(C91:N91) -> 0
B92: =B78 -> 0 | O92: =SUM(C92:N92) -> 0
B93: Total Retainer Contracts | C93: =SUM(C82:C92) -> 1.1 | D93: =SUM(D82:D92) -> 1.25 | E93: =SUM(E82:E92) -> 1.65 | F93: =SUM(F82:F92) -> 1.95 | G93: =SUM(G82:G92) -> 1.8 | H93: =SUM(H82:H92) -> 1.65 | I93: =SUM(I82:I92) -> 1.8 | J93: =SUM(J82:J92) -> 1.85 | ... O93: =SUM(O82:O92) -> 19 | P93: =O93/12 -> 1.5833333 | Q93: Av/Month
B95: Custom Development Sales
C96: 44927 | D96: 44958 | E96: 44986 | F96: 45017 | G96: 45047 | H96: 45078 | I96: 45108 | J96: 45139 | K96: 44805 | L96: 45200 | M96: 45231 | N96: 45261 | O96: Total
B97: =B82 -> Alfa Electronics | C97: =C82*$C68 -> 61560 | D97: =D82*$C68 -> 61560 | E97: =E82*$C68 -> 61560 | F97: =F82*$C68 -> 61560 | G97: =G82*$C68 -> 61560 | H97: =H82*$C68 -> 61560 | I97: =I82*$C68 -> 61560 | J97: =J82*$C68 -> 61560 | ... N97: =N82*$C68 -> 61560 | O97: =SUM(C97:N97) -> 738720
B98: =B83 -> VIPFirst | C98: =C83*$C69 -> 17100 | D98: =D83*$C69 -> 42750 | E98: =E83*$C69 -> 42750 | F98: =F83*$C69 -> 42750 | G98: =G83*$C69 -> 25650 | H98: =H83*$C69 -> 0 | I98: =I83*$C69 -> 0 | J98: =J83*$C69 -> 0 | ... N98: =N83*$C69 -> 0 | O98: =SUM(C98:N98) -> 171000
B99: =B84 -> Project 1 | C99: =C84*$C$70 -> 0 | D99: =D84*$C$70 -> 0 | E99: =E84*$C$70 -> 48735 | F99: =F84*$C$70 -> 48735 | G99: =G84*$C$70 -> 48735 | H99: =H84*$C$70 -> 29241 | I99: =I84*$C$70 -> 19494 | J99: =J84*$C$70 -> 0 | ... N99: =N84*$C$70 -> 0 | O99: =SUM(C99:N99) -> 194940
B100: =B85 -> Project 2 | C100: =C85*$C$71 -> 0 | D100: =D85*$C$71 -> 0 | E100: =E85*$C$71 -> 0 | F100: =F85*$C$71 -> 0 | G100: =G85*$C$71 -> 77976 | H100: =H85*$C$71 -> 25992 | I100: =I85*$C$71 -> 64980 | J100: =J85*$C$71 -> 64980 | ... N100: =N85*$C$71 -> 0 | O100: =SUM(C100:N100) -> 259920
B101: =B86 -> Project 3 | C101: =C86*$C$72 -> 0 | D101: =D86*$C$72 -> 0 | E101: =E86*$C$72 -> 0 | F101: =F86*$C$72 -> 77976 | G101: =G86*$C$72 -> 25992 | H101: =H86*$C$72 -> 0 | I101: =I86*$C$72 -> 0 | J101: =J86*$C$72 -> 64980 | ... N101: =N86*$C$72 -> 25992 | O101: =SUM(C101:N101) -> 259920
B102: =B87 -> Project 4 | C102: =C87*$C73 -> 0 | D102: =D87*$C73 -> 0 | E102: =E87*$C73 -> 0 | F102: =F87*$C73 -> 0 | G102: =G87*$C73 -> 0 | H102: =H87*$C73 -> 0 | I102: =I87*$C73 -> 97470 | J102: =J87*$C73 -> 32490 | ... N102: =N87*$C73 -> 0 | O102: =SUM(C102:N102) -> 324900
B103: =B88 -> Project 5 | C103: =C88*$C74 -> 0 | D103: =D88*$C74 -> 0 | E103: =E88*$C74 -> 0 | F103: =F88*$C74 -> 0 | G103: =G88*$C74 -> 0 | H103: =H88*$C74 -> 81225 | I103: =I88*$C74 -> 0 | J103: =J88*$C74 -> 81225 | ... N103: =N88*$C74 -> 81225 | O103: =SUM(C103:N103) -> 324900
B104: =B89 -> Project 6 | C104: =C89*$C75 -> 0 | D104: =D89*$C75 -> 0 | E104: =E89*$C75 -> 58482 | F104: =F89*$C75 -> 58482 | G104: =G89*$C75 -> 0 | H104: =H89*$C75 -> 58482 | I104: =I89*$C75 -> 58482 | J104: =J89*$C75 -> 0 | ... N104: =N89*$C75 -> 0 | O104: =SUM(C104:N104) -> 389880
B105: =B90 -> 0 | C105: =C90*$C76 -> 0 | D105: =D90*$C76 -> 0 | E105: =E90*$C76 -> 0 | F105: =F90*$C76 -> 0 | G105: =G90*$C76 -> 0 | H105: =H90*$C76 -> 0 | I105: =I90*$C76 -> 0 | J105: =J90*$C76 -> 0 | ... N105: =N90*$C76 -> 0 | O105: =SUM(C105:N105) -> 0
B106: =B91 -> 0 | C106: =C91*$C77 -> 0 | D106: =D91*$C77 -> 0 | E106: =E91*$C77 -> 0 | F106: =F91*$C77 -> 0 | G106: =G91*$C77 -> 0 | H106: =H91*$C77 -> 0 | I106: =I91*$C77 -> 0 | J106: =J91*$C77 -> 0 | ... N106: =N91*$C77 -> 0 | O106: =SUM(C106:N106) -> 0
B107: =B92 -> 0 | C107: =C92*$C78 -> 0 | D107: =D92*$C78 -> 0 | E107: =E92*$C78 -> 0 | F107: =F92*$C78 -> 0 | G107: =G92*$C78 -> 0 | H107: =H92*$C78 -> 0 | I107: =I92*$C78 -> 0 | J107: =J92*$C78 -> 0 | ... N107: =N92*$C78 -> 0 | O107: =SUM(C107:N107) -> 0
B108: Custom Development Sales | C108: =SUM(C97:C107) -> 78660 | D108: =SUM(D97:D107) -> 104310 | E108: =SUM(E97:E107) -> 211527 | F108: =SUM(F97:F107) -> 289503 | G108: =SUM(G97:G107) -> 239913 | H108: =SUM(H97:H107) -> 256500 | I108: =SUM(I97:I107) -> 301986 | J108: =SUM(J97:J107) -> 305235 | ... O108: =SUM(O97:O107) -> 2664180 | P108: =O108/O93 -> 140220 | Q108: =O108/C64 -> 41
B110: 3. Products
B111: Average Product Price | C111: =36000*(1+C6) -> 41040
B113: Products
C114: 44927 | D114: 44958 | E114: 44986 | F114: 45017 | G114: 45047 | H114: 45078 | I114: 45108 | J114: 45139 | K114: 44805 | L114: 45200 | M114: 45231 | N114: 45261 | O114: Total
B115: # of Products Sold | F115: 1 | J115: 1 | N115: 1 | O115: =SUM(C115:N115) -> 3
B116: =B111 -> Average Product Price | C116: =$C111 -> 41040 | D116: =$C111 -> 41040 | E116: =$C111 -> 41040 | F116: =$C111 -> 41040 | G116: =$C111 -> 41040 | H116: =$C111 -> 41040 | I116: =$C111 -> 41040 | J116: =$C111 -> 41040 | ... N116: =$C111 -> 41040
B117: Products Sales | C117: =C115*C116 -> 0 | D117: =D115*D116 -> 0 | E117: =E115*E116 -> 0 | F117: =F115*F116 -> 41040 | G117: =G115*G116 -> 0 | H117: =H115*H116 -> 0 | I117: =I115*I116 -> 0 | J117: =J115*J116 -> 41040 | ... N117: =N115*N116 -> 41040 | O117: =SUM(C117:N117) -> 123120
B119: 4. Websites
...

Sheet Allocation
B2: Aura Systems - Software Department
B3: Income Budget based on Allocation
B4: Financial Numbers in EGP
B6: Custom Development
C7: 2021 | D7: % | F7: Improvement Factors
B8: Headcount | C8: 7.5 | F8: Training | G8: 0.05
B9: Revenue | C9: =Growth!I8 -> 1517000 | F9: Pricing | G9: =C21/C10-1 -> #DIV/0!
B10: Monthly Price | F10: Process | G10: 0.03
B11: Cost of Sales | D11: =C11/C9 -> 0 | F11: Allocation | G11: 0.03
B12: Salaries | D12: =C12/C9 -> 0 | F12: Total | G12: =SUM(G8:G11) -> #DIV/0!
B13: OpEx | D13: =C13/C9 -> 0
B14: Taxes | D14: =C14/C9 -> 0
B15: Earnings | C15: =[9]Software!$O$34 -> 207907.42 | D15: =C15/C9 -> 0.13705169
B16: Revenue per Head | C16: =C9/C8 -> 202266.67
B17: Earnings per Head | C17: =C15/C8 -> 27720.989
C19: 2022
B20: Headcount | C20: 12
B21: =B10 -> Monthly Price | C21: =Activity!C64 -> 64980
B22: % Improvement | C22: =G12 -> #DIV/0!
B23: Revenue per head | C23: =C16*(1+C22) -> #DIV/0!
B24: Revenue | C24: =C20*C23 -> #DIV/0!
B25: Cost of Sales | C25: =D11*C24 -> #DIV/0!
B26: Salaries
B27: OpEx | C27: =D13*C24 -> #DIV/0!
B28: Taxes | C28: =D14*C24 -> #DIV/0!
B29: Earnings | C29: =C24-SUM(C25:C28) -> #DIV/0! | D29: =C29/C24 -> #DIV/0!
B30: Earnings per Head | C30: =C29/C20 -> #DIV/0!
B33: Websites
C34: 2021 | D34: % | F34: Improvement Factors
B35: Headcount | C35: 3 | F35: Training | G35: 0.05
B36: Revenue | C36: =[9]Websites!$O$11 -> 502514.99 | F36: Pricing | G36: =C48/C37-1 -> 0.47730405
B37: Average Contract | C37: =[9]Websites!$O$47 -> 22321.129 | F37: Process | G37: 0.1
B38: Cost of Sales | C38: =[9]Websites!$O$14 -> 64953.426 | D38: =C38/C36 -> 0.12925669 | F38: Allocation | G38: 0.03
B39: Salaries | C39: =[9]Websites!$O$20 -> 298750.89 | D39: =C39/C36 -> 0.59451139 | F39: Total | G39: =SUM(G35:G38) -> 0.65730405
B40: OpEx | C40: =[9]Websites!$O$25 -> 2058.05 | D40: =C40/C36 -> 0.0040954997
B41: Taxes | C41: =[9]Websites!$O$30 -> 44645.245 | D41: =C41/C36 -> 0.088843608
B42: Earnings | C42: =[9]Websites!$O$32 -> 92107.385 | D42: =C42/C36 -> 0.18329281
B43: Revenue per Head
B44: Earnings per Head | C44: =[9]Websites!$O$38*12 -> 277847.18
C46: 2022
B47: Headcount | C47: 6
B48: Average Contract | C48: =Activity!P136 -> 32975.094
B49: % Improvement | C49: =G39 -> 0.65730405
B50: Revenue per head | C50: =C43*(1+C49) -> 0
B51: Revenue | C51: =C47*C50 -> 0
B52: Cost of Sales | C52: =D38*(C51*0.75) -> 0
B53: Salaries | C53: =C39/C35*C47*1.15 -> 687127.04
B54: OpEx | C54: =D40*C51 -> 0
B55: Taxes | C55: =D41*C51 -> 0
B56: Earnings | C56: =C51-SUM(C52:C55) -> -687127.04 | D56: =C56/C51 -> #DIV/0!
B57: Earnings per Head | C57: =C56/C47 -> -114521.17

Sheet Capacity
B2: Aura Systems - Software Department
B3: Income Budget based on Capacity
B4: Financial Numbers in EGP
B6: 2026 | C6: Product | D6: PHP | E6: .Net | F6: Mobile | H6: Websites | I6: Design
B7: Head Count | C7: 1 | D7: 3 | E7: 3 | F7: 1 | H7: 1 | I7: 1 | J7: =SUM(D7:I7) -> 9
B8: Avg billable hours per Emp | C8: 160 | D8: 120 | E8: 120 | F8: 120 | H8: 120 | I8: 60
C9: 0.9 | D9: 0.85 | E9: 0.85 | F9: 0.9 | H9: 0.8 | I9: 0.55
B10: Hour Price | C10: =Growth!V7 -> 1250 | D10: =Growth!V8 -> 1150 | E10: =Growth!V9 -> 1150 | F10: =Growth!V10 -> 1150 | H10: =Growth!V12 -> 1050 | I10: =Growth!V13 -> 1050
B11: Total | C11: =C7*C8*C10*12*C9*1.14 -> 2462400 | D11: =D7*D8*D10*12*D9*1.14 -> 4813992 | E11: =E7*E8*E10*12*E9*1.14 -> 4813992 | F11: =F7*F8*F10*12*F9*1.14 -> 1699056 | H11: =H7*H8*H10*12*H9*1.14 -> 1378944 | I11: =I7*I8*I10*12*I9*1.14 -> 474012 | J11: =SUM(D11:I11) -> 13179996 | K11: =J11/J7 -> 1464444
C12: =C8*C9 -> 144 | D12: =D8*D9 -> 102 | E12: =E8*E9 -> 102 | F12: =F8*F9 -> 108 | H12: =H8*H9 -> 96 | I12: =I8*I9 -> 33
B13: Monthly | C13: =C12*C10 -> 180000 | D13: =D12*D10 -> 117300 | E13: =E12*E10 -> 117300 | F13: =F12*F10 -> 124200 | H13: =H12*H10 -> 100800 | I13: =I12*I10 -> 34650
B16: 2025 | C16: Product | D16: PHP | E16: .NET | F16: Mobile | H16: Websites | I16: Design
B17: Head Count | C17: 1 | D17: 3 | E17: 3 | F17: 1 | H17: 1.5 | I17: 1 | J17: =SUM(D17:I17) -> 9.5
B18: Avg billable hours per Emp | C18: 160 | D18: =D8 -> 120 | E18: 120 | F18: =F8 -> 120 | H18: =H8 -> 120 | I18: =I8 -> 60
C19: =C21/1.14/C20/12/C17/C18 -> 0.88894419 | D19: =D21/1.14/D20/12/D17/D18 -> 0.76613259 | E19: =E21/1.14/E20/12/E17/E18 -> 0.73194642 | F19: =F21/1.14/F20/12/F17/F18 -> 0.90142667 | H19: =H21/1.14/H20/12/H17/H18 -> 0.32223774 | I19: =I21/1.14/I20/12/I17/I18 -> 0.43731339
B20: Hour Price | C20: =Growth!T7 -> 1100 | D20: =Growth!T8 -> 975 | E20: =Growth!T9 -> 975 | F20: =Growth!T10 -> 975 | H20: =Growth!T12 -> 875 | I20: =Growth!T13 -> 875
B21: Total | C21: =Growth!M7 -> 2140293.1 | D21: =Growth!M8 -> 3678723.6 | E21: =Growth!M9 -> 3514572.5 | F21: =Growth!M10 -> 1442787.5 | H21: =Growth!M12 -> 694293.43 | I21: =Growth!M13 -> 314078.48 | J21: =SUM(D21:I21) -> 9644455.4 | K21: =J21/J17 -> 1015205.8
B22: Billable Hours per Month/Emp | C22: =C19*C18 -> 142.23107 | D22: =D19*D18 -> 91.935911 | E22: =E19*E18 -> 87.833571 | F22: =F19*F18 -> 108.1712 | H22: =H19*H18 -> 38.668528 | I22: =I19*I18 -> 26.238803
B23: Total Worked Hours | C23: 100 | D23: 100 | E23: 100 | F23: 100 | H23: 100 | I23: =436.47/11 -> 39.679091
B24: Billable/total | C24: =C22/C23 -> 1.4223107 | D24: =D22/D23 -> 0.91935911 | E24: =E22/E23 -> 0.87833571 | F24: =F22/F23 -> 1.081712 | H24: =H22/H23 -> 0.38668528 | I24: =I22/I23 -> 0.66127531
B25: Improvement Needed 2024 | C25: =C9/C19 -> 1.012437 | D25: =D9/D19 -> 1.1094685 | E25: =E9/E19 -> 1.1612872 | F25: =F9/F19 -> 0.99841732 | H25: =H9/H19 -> 2.4826391 | I25: =I9/I19 -> 1.2576793
D27: =(110-D22)*D17*12*D20 -> 634049.51 | E27: =(110-E22)*E17*12*E20 -> 778041.67 | H27: =(110-H22)*H17*12*H20 -> 1123470.7

Sheet Collection
A1: Aura Systems - Software Department
A2: Income Budget based on Activities
A3: Financial Numbers in EGP
A5: VAT Rate | B5: 0.14
A7: 0. Summary
A8: Collection Method
A9: Activity | B9: Total | C9: 2025 | D9: Increase
A10: Support Contracts | B10: 0 | C10: 0
A11: PHP | B11: =B45 -> 5074263.8 | C11: =Growth!M8 -> 3678723.6 | D11: =Table124[[#This Row],[Total]]/Table124[[#This Row],[2025]]-100% -> 0.37935447
A12: Products | B12: =B71 -> 3014068 | C12: =Growth!M7 -> 2140293.1 | D12: =Table124[[#This Row],[Total]]/Table124[[#This Row],[2025]]-100% -> 0.40825009
A13: Websites | B13: =B110 -> 1027762 | C13: =Growth!M12 -> 694293.43 | D13: =Table124[[#This Row],[Total]]/Table124[[#This Row],[2025]]-100% -> 0.48029918
A14: Hosting | B14: =B84 -> 945997.36 | C14: =Growth!M14 -> 376829.19 | D14: =Table124[[#This Row],[Total]]/Table124[[#This Row],[2025]]-100% -> 1.5104142
A15: Mobile Developmet | B15: =B122 -> 3004332.9 | C15: =Growth!M10 -> 1442787.5 | D15: =Table124[[#This Row],[Total]]/Table124[[#This Row],[2025]]-100% -> 1.0823115
A16: Design | B16: =B134 -> 411106.03 | C16: =Growth!M13 -> 314078.48 | D16: =Table124[[#This Row],[Total]]/Table124[[#This Row],[2025]]-100% -> 0.30892775
A17: .NET | B17: =B58 -> 2584367 | C17: =Growth!M9 -> 3514572.5 | D17: =Table124[[#This Row],[Total]]/Table124[[#This Row],[2025]]-100% -> -0.26467101
B18: =SUBTOTAL(109,Table124[Total]) -> 16061897 | C18: =SUBTOTAL(109,Table124[2025]) -> 12161578 | D18: =(Table124[[#Totals],[Total]]/Table124[[#Totals],[2025]])-100% -> 0.32070834
A22: 2025
A23: Activity | B23: Beginning Balance | C23: End Balance | D23: Average
A24: Support Contracts | B24: 0 | C24: 0
A25: PHP | B25: =[10]Total!$E$3 -> 330066.52 | C25: =[10]Total!$R$3 -> 852855.96 | D25: =(B25+C25)/2 -> 591461.24
A26: Products | B26: =[10]Total!$E$18 -> 0 | C26: =[10]Total!$R$18 -> 909243.85 | D26: =(B26+C26)/2 -> 454621.92
A27: Websites | B27: =[10]Total!$E$13 -> 245176.91 | C27: =[10]Total!$R$13 -> 352236.76 | D27: =(B27+C27)/2 -> 298706.83
A28: Hosting | B28: =[10]Total!$E$33 -> 152020.96 | C28: =[10]Total!$R$33 -> 351300.14 | D28: =(B28+C28)/2 -> 251660.55
A29: Mobile Developmet | B29: =[10]Total!$E$8 -> 451215 | C29: =[10]Total!$R$8 -> 1405820.7 | D29: =(B29+C29)/2 -> 928517.86
A30: =A16 -> Design | B30: =[10]Total!$E$28 -> 78240.2 | C30: =[10]Total!$R$28 -> 135950.71 | D30: =(B30+C30)/2 -> 107095.45
A31: =A17 -> .NET | B31: =[10]Total!$E$23 -> 220381 | C31: =[10]Total!$R$23 -> 235120.93 | D31: =(B31+C31)/2 -> 227750.97
A32: Total | B32: =SUM(B24:B31) -> 1477100.6 | C32: =SUM(C24:C31) -> 4242529.1 | D32: =(B32+C32)/2 -> 2859814.8
A36: PHP
A37: Average Contract per month | B37: =SUM([10]Total!$R$4:$R$5)/12 -> 347717.47
A38: Average Collection per Month | B38: =SUM([10]Total!$R$6:$R$7)/12 -> 353365.26
A39: Collection Months | B39: =D25/B38 -> 1.6737956
A41: =A36 -> PHP | F41: 1 | G41: 2 | H41: 3 | I41: 4 | J41: 5 | K41: 6 | L41: 7 | M41: 8 | N41: 9 | O41: 10 | P41: 11 | Q41: 12
A42: Jan2026 Balance | B42: =C25 -> 852855.96 | D42: 0.2 | F42: 0.6 | G42: 0.4
A43: Collection Months 2026 | B43: =(F46+B39)/2 -> 2.0168978 | D43: 0.4 | F43: 0.3 | G43: 0.3 | H43: 0.3 | I43: 0.1
A44: Collection per month | B44: =B42/B43 -> 422855.31 | D44: 0.4 | F44: 0.2 | G44: 0.2 | H44: 0.2 | I44: 0.2 | J44: 0.2
A45: Total | B45: =B44*12 -> 5074263.8 | D45: Coll | F45: =($D$42*F42)+($D$43*F43)+($D$44*F44) -> 0.32 | G45: =($D$42*G42)+($D$43*G43)+($D$44*G44) -> 0.28 | H45: =($D$42*H42)+($D$43*H43)+($D$44*H44) -> 0.2 | I45: =($D$42*I42)+($D$43*I43)+($D$44*I44) -> 0.12 | J45: =($D$42*J42)+($D$43*J43)+($D$44*J44) -> 0.08 | K45: =($D$42*K42)+($D$43*K43)+($D$44*K44) -> 0 | L45: =($D$42*L42)+($D$43*L43)+($D$44*L44) -> 0 | M45: =($D$42*M42)+($D$43*M43)+($D$44*M44) -> 0 | ... Q45: =($D$42*Q42)+($D$43*Q43)+($D$44*Q44) -> 0
F46: =SUMPRODUCT(F45:Q45,F41:Q41) -> 2.36
A49: .Net
A50: Average Contract per month | B50: =SUM([10]Total!$R$24:$R$25)/12 -> 299536.43
A51: Average Collection per Month | B51: =SUM([10]Total!$R$26:$R$27)/12 -> 298308.11
A52: Collection Months | B52: =D31/B51 -> 0.76347562
A54: =A49 -> .Net | F54: 1 | G54: 2 | H54: 3 | I54: 4 | J54: 5 | K54: 6 | L54: 7 | M54: 8 | N54: 9 | O54: 10 | P54: 11 | Q54: 12
A55: Jan2026 Balance | B55: =C31 -> 235120.93 | D55: 0.1 | F55: 1 | G55: 0
A56: Collection Months 2026 | B56: =(F59+B52)/2 -> 1.0917378 | D56: 0.4 | F56: 0.6 | G56: 0.4 | H56: 0
A57: Collection per month | B57: =B55/B56 -> 215363.92 | D57: 0.5 | F57: 0.4 | G57: 0.4 | H57: 0.2 | I57: 0
A58: Total | B58: =B57*12 -> 2584367 | D58: Coll | F58: =($D$55*F55)+($D56*F56)+($D57*F57) -> 0.54 | G58: =($D$42*G55)+($D$43*G56)+($D$44*G57) -> 0.32 | H58: =($D$42*H55)+($D$43*H56)+($D$44*H57) -> 0.08 | I58: =($D$42*I55)+($D$43*I56)+($D$44*I57) -> 0 | J58: =($D$42*J55)+($D$43*J56)+($D$44*J57) -> 0 | K58: =($D$42*K55)+($D$43*K56)+($D$44*K57) -> 0 | L58: =($D$42*L55)+($D$43*L56)+($D$44*L57) -> 0 | M58: =($D$42*M55)+($D$43*M56)+($D$44*M57) -> 0 | N58: =($D$42*N55)+($D$43*N56)+($D$44*N57) -> 0 | ... Q58: =($D$42*Q55)+($D$43*Q56)+($D$44*Q57) -> 0
F59: =SUMPRODUCT(F58:Q58,F54:Q54) -> 1.42
A62: Products 2025
A63: Average Contract per month | B63: =SUM([10]Total!$R$19:$R$20)/12 -> 166575.38
A64: Average Collection per Month | B64: =SUM([10]Total!$R$21:$R$22)/12 -> 156125.38
A65: Collection Months | B65: 3
A67: Products 2026 | F67: 1 | G67: 2 | H67: 3 | I67: 4 | J67: 5 | K67: 6 | L67: 7 | M67: 8 | N67: 9 | O67: 10 | P67: 11 | Q67: 12
A68: Jan2026 Balance | B68: =C26 -> 909243.85 | D68: 0.3 | F68: 0 | G68: 0.1 | H68: 0.3 | I68: 0.3 | J68: 0.3
A69: Collection Months 2026 | B69: =(F72+B65)/2 -> 3.62 | D69: 0.1 | F69: 0.2 | G69: 0.2 | H69: 0.2 | I69: 0.2 | J69: 0.2
A70: Collection per month | B70: =B68/B69 -> 251172.33 | D70: 0.6 | F70: 0.4 | G70: 0.1 | H70: 0.1 | I70: 0.1 | J70: 0.1 | K70: 0.1 | L70: 0.1 | M70: 0.1 | N70: 0.1 | O70: 0.1
A71: Total | B71: =B70*12 -> 3014068 | D71: Coll | F71: =($D$68*F68)+($D$69*F69)+($D$70*F70) -> 0.26 | G71: =($D$68*G68)+($D$69*G69)+($D$70*G70) -> 0.11 | H71: =($D$68*H68)+($D$69*H69)+($D$70*H70) -> 0.17 | I71: =($D$68*I68)+($D$69*I69)+($D$70*I70) -> 0.17 | J71: =($D$68*J68)+($D$69*J69)+($D$70*J70) -> 0.17 | K71: =($D$68*K68)+($D$69*K69)+($D$70*K70) -> 0.06 | L71: =($D$42*L68)+($D$43*L69)+($D$44*L70) -> 0.04 | M71: =($D$42*M68)+($D$43*M69)+($D$44*M70) -> 0.04 | N71: =($D$42*N68)+($D$43*N69)+($D$44*N70) -> 0.04 | O71: =($D$42*O68)+($D$43*O69)+($D$44*O70) -> 0.04 | P71: =($D$42*P68)+($D$43*P69)+($D$44*P70) -> 0 | Q71: =($D$42*Q68)+($D$43*Q69)+($D$44*Q70) -> 0
F72: =SUMPRODUCT(F71:Q71,F67:Q67) -> 4.24
A75: Hosting 2025
A76: Average Contract per month | B76: =SUM([10]Total!$R$34:$R$35)/12 -> 44388.088
A77: Average Collection per Month | B77: =SUM([10]Total!$R$36:$R$37)/12 -> 37491.318
A78: Collection Months | B78: =D28/B77 -> 6.712502
A80: Hosting 2026 | F80: 1 | G80: 2 | H80: 3 | I80: 4 | J80: 5 | K80: 6 | L80: 7 | M80: 8 | N80: 9 | O80: 10 | P80: 11 | Q80: 12
A81: Jan2026 Balance | B81: =C28 -> 351300.14 | D81: 0.9 | G81: 1
A82: Collection Months 2026 | B82: =(F85+B78)/2 -> 4.456251 | D82: 0.1 | I82: 1
A83: Collection per month | B83: =B81/B82 -> 78833.113
A84: Total | B84: =B83*12 -> 945997.36 | D84: Coll | F84: =($D$81*F81)+($D$82*F82)+($D$83*F83) -> 0 | G84: =($D$81*G81)+($D$82*G82)+($D$83*G83) -> 0.9 | H84: =($D$81*H81)+($D$82*H82)+($D$83*H83) -> 0 | I84: =($D$81*I81)+($D$82*I82)+($D$83*I83) -> 0.1 | J84: =($D$81*J81)+($D$82*J82)+($D$83*J83) -> 0 | K84: =($D$81*K81)+($D$82*K82)+($D$83*K83) -> 0 | L84: =($D$42*L81)+($D$43*L82)+($D$44*L83) -> 0 | M84: =($D$42*M81)+($D$43*M82)+($D$44*M83) -> 0 | N84: =($D$42*N81)+($D$43*N82)+($D$44*N83) -> 0 | O84: =($D$42*O81)+($D$43*O82)+($D$44*O83) -> 0 | P84: =($D$42*P81)+($D$43*P82)+($D$44*P83) -> 0 | Q84: =($D$42*Q81)+($D$43*Q82)+($D$44*Q83) -> 0
F85: =SUMPRODUCT(F84:Q84,F80:Q80) -> 2.2
A88: Support 2023
A89: Average Contract per month | B89: 0
A90: Average Collection per Month | B90: 0
A91: Collection Months | B91: =D24/B90 -> #DIV/0!
A93: Support 2024 | F93: 1 | G93: 2 | H93: 3 | I93: 4 | J93: 5 | K93: 6 | L93: 7 | M93: 8 | N93: 9 | O93: 10 | P93: 11 | Q93: 12
A94: Jan2024 Balance | B94: =C24 -> 0 | D94: 0.9 | F94: 1
A95: Collection Months 2024 | B95: =(F98+B91)/2 -> #DIV/0! | D95: 0.1 | G95: 1
A96: Collection per month | B96: =B94/B95 -> #DIV/0! | D96: 0 | F96: 0 | G96: 0 | H96: 0
A97: Total | B97: =B96*12 -> #DIV/0! | D97: Coll | F97: =($D$94*F94)+($D$95*F95)+($D$96*F96) -> 0.9 | G97: =($D$94*G94)+($D$95*G95)+($D$96*G96) -> 0.1 | H97: =($D$94*H94)+($D$95*H95)+($D$96*H96) -> 0 | I97: =($D$94*I94)+($D$95*I95)+($D$96*I96) -> 0 | J97: =($D$94*J94)+($D$95*J95)+($D$96*J96) -> 0 | K97: =($D$94*K94)+($D$95*K95)+($D$96*K96) -> 0 | L97: =($D$42*L94)+($D$43*L95)+($D$44*L96) -> 0 | M97: =($D$42*M94)+($D$43*M95)+($D$44*M96) -> 0 | N97: =($D$42*N94)+($D$43*N95)+($D$44*N96) -> 0 | O97: =($D$42*O94)+($D$43*O95)+($D$44*O96) -> 0 | P97: =($D$42*P94)+($D$43*P95)+($D$44*P96) -> 0 | Q97: =($D$42*Q94)+($D$43*Q95)+($D$44*Q96) -> 0
F98: =SUMPRODUCT(F97:Q97,F93:Q93) -> 1.1
A101: Websites 2025
A102: Average Contract per month | B102: =SUM([10]Total!$R$14:$R$15)/12 -> 62825.613
A103: Average Collection per Month | B103: =SUM([10]Total!$R$16:$R$17)/12 -> 67044.818
A104: Collection Months | B104: =D27/B103 -> 4.4553307
A106: Websites 2026 | F106: 1 | G106: 2 | H106: 3 | I106: 4 | J106: 5 | K106: 6 | L106: 7 | M106: 8 | N106: 9 | O106: 10 | P106: 11 | Q106: 12
A107: Jan2026 Balance | B107: =C27 -> 352236.76 | D107: 0.35 | G107: 0.4 | I107: 0.4 | K107: 0.2
A108: Collection Months 2026 | B108: =(F111+B104)/2 -> 4.1126653 | D108: 0.35 | G108: 0.3 | I108: 0.2 | K108: 0.5
A109: Collection per month | B109: =B107/B108 -> 85646.833 | D109: 0.3 | F109: 0.3 | G109: 0.3 | H109: 0.3 | I109: 0.1
A110: Total | B110: =B109*12 -> 1027762 | D110: Coll | F110: =($D107*F107)+($D108*F108)+($D109*F109) -> 0.09 | G110: =($D$81*G107)+($D$82*G108)+($D$83*G109) -> 0.39 | H110: =($D$81*H107)+($D$82*H108)+($D$83*H109) -> 0 | I110: =($D$81*I107)+($D$82*I108)+($D$83*I109) -> 0.38 | J110: =($D$81*J107)+($D$82*J108)+($D$83*J109) -> 0 | K110: =($D$81*K107)+($D$82*K108)+($D$83*K109) -> 0.23 | L110: =($D$42*L107)+($D$43*L108)+($D$44*L109) -> 0 | M110: =($D$42*M107)+($D$43*M108)+($D$44*M109) -> 0 | N110: =($D$42*N107)+($D$43*N108)+($D$44*N109) -> 0 | O110: =($D$42*O107)+($D$43*O108)+($D$44*O109) -> 0 | P110: =($D$42*P107)+($D$43*P108)+($D$44*P109) -> 0 | Q110: =($D$42*Q107)+($D$43*Q108)+($D$44*Q109) -> 0
F111: =SUMPRODUCT(F110:Q110,F106:Q106) -> 3.77
A113: Mobile Software 2025
A114: Average Contract per month | B114: =SUM([10]Total!$R$9:$R$10)/12 -> 157722.47
A115: Average Collection per Month | B115: =SUM([10]Total!$R$11:$R$12)/12 -> 150237.21
A116: Collection Months | B116: =D29/B115 -> 6.1803456
A118: Mobile Software 2026 | F118: 1 | G118: 2 | H118: 3 | I118: 4 | J118: 5 | K118: 6 | L118: 7 | M118: 8 | N118: 9 | O118: 10 | P118: 11 | Q118: 12
A119: Jan2026 Balance | B119: =C29 -> 1405820.7 | D119: 0.1 | F119: 0.4 | G119: 0.4 | H119: 0.2
A120: Collection Months 2026 | B120: =(F123+B116)/2 -> 5.6151728 | D120: 0.3 | F120: 0.3 | J120: 0.3 | M120: 0.4
A121: Collection per month | B121: =B119/B120 -> 250361.08 | D121: 0.6 | F121: 0.2 | I121: 0.2 | L121: 0.2 | O121: 0.2 | Q121: 0.2
A122: Total | B122: =B121*12 -> 3004332.9 | D122: Coll | F122: =($D119*F119)+($D120*F120)+($D121*F121) -> 0.25 | G122: =($D$42*G119)+($D$43*G120)+($D$44*G121) -> 0.08 | H122: =($D$42*H119)+($D$43*H120)+($D$44*H121) -> 0.04 | I122: =($D$42*I119)+($D$43*I120)+($D$44*I121) -> 0.08 | J122: =($D$42*J119)+($D$43*J120)+($D$44*J121) -> 0.12 | K122: =($D$42*K119)+($D$43*K120)+($D$44*K121) -> 0 | L122: =($D$42*L119)+($D$43*L120)+($D$44*L121) -> 0.08 | M122: =($D$42*M119)+($D$43*M120)+($D$44*M121) -> 0.16 | N122: =($D$42*N119)+($D$43*N120)+($D$44*N121) -> 0 | ... Q122: =($D$42*Q119)+($D$43*Q120)+($D$44*Q121) -> 0.08
F123: =SUMPRODUCT(F122:Q122,F118:Q118) -> 5.05
A125: Design 2025
A126: Average Contract per month | B126: =SUM([10]Total!$R$29:$R$30)/12 -> 25941.709
A127: Average Collection per Month | B127: =SUM([10]Total!$R$31:$R$32)/12 -> 27950
...

Sheet Result
B2: Aura Systems - Software Department
B3: Income Budget Results
B4: Financial Numbers in EGP
H5: 2026 | L5: 2025 | P5: Pricing Structure
B6: Item | C6: Extrapolation | D6: Capacity | E6: Collection | F6: Collection Adj | G6: Average | H6: Final | I6: Monthly | J6: Hours/Mth | K6: Employees | L6: Final | M6: Monthly | N6: Monthly +% | P6: 2022 | Q6: 2023 | R6: 2024 | S6: 2025 | T6: 2026 | U6: % | V6: USD$
B7: =Growth!B7 -> Products | C7: =Growth!N7 -> 2000000 | D7: =Capacity!C11 -> 2462400 | E7: =Collection!B12 -> 3014068 | F7: =E7*1.3 -> 3918288.4 | G7: =AVERAGE(C7:E7) -> 2492156 | H7: 2500000 | I7: =H7/12 -> 208333.33 | J7: =I7/(Table57[[#This Row],[2025]]*1.14) -> 166.13503 | K7: 1 | L7: =Growth!M7 -> 2140293.1 | M7: =L7/12 -> 178357.76 | N7: =M7*Table57[[#This Row],[%]] -> 218893.62 | P7: =Table5[[#This Row],[2022]] -> 575 | Q7: =Table5[[#This Row],[2023]] -> 625 | R7: =Table5[[#This Row],[2024]] -> 800 | S7: =Table5[[#This Row],[2025]] -> 1100 | T7: 1350 | U7: =Table57[[#This Row],[2026]]/Table57[[#This Row],[2025]] -> 1.2272727 | V7: =Table57[[#This Row],[2026]]/$T$15 -> 27.55102
B8: =Growth!B8 -> PHP | C8: =Growth!N8 -> 4700000 | D8: =Capacity!D11 -> 4813992 | E8: =Collection!B11 -> 5074263.8 | F8: =E8*1.3 -> 6596542.9 | G8: =AVERAGE(C8:E8) -> 4862751.9 | H8: 4800000 | I8: =H8/12 -> 400000 | J8: =I8/(Table57[[#This Row],[2025]]*1.14) -> 359.87404 | K8: 3 | L8: =Growth!M8 -> 3678723.6 | M8: =L8/12 -> 306560.3 | N8: =M8*Table57[[#This Row],[%]] -> 361583.94 | P8: =Table5[[#This Row],[2022]] -> 575 | Q8: =Table5[[#This Row],[2023]] -> 625 | R8: =Table5[[#This Row],[2024]] -> 800 | S8: =Table5[[#This Row],[2025]] -> 975 | T8: =Table5[[#This Row],[2026]] -> 1150 | U8: =Table57[[#This Row],[2026]]/Table57[[#This Row],[2025]] -> 1.1794872 | V8: =Table57[[#This Row],[2026]]/$T$15 -> 23.469388
B9: .NET | C9: =Growth!N9 -> 4400000 | D9: =Capacity!E11 -> 4813992 | E9: =Collection!B17 -> 2584367 | F9: =E9*1.3 -> 3359677.1 | G9: =AVERAGE(C9:E9) -> 3932786.3 | H9: 4200000 | I9: =H9/12 -> 350000 | J9: =I9/(Table57[[#This Row],[2025]]*1.14) -> 314.88979 | K9: 3 | L9: =Growth!M9 -> 3514572.5 | M9: =L9/12 -> 292881.04 | N9: =M9*Table57[[#This Row],[%]] -> 345449.43 | P9: =Table5[[#This Row],[2022]] -> 525 | Q9: =Table5[[#This Row],[2023]] -> 575 | R9: =Table5[[#This Row],[2024]] -> 800 | S9: =Table5[[#This Row],[2025]] -> 975 | T9: =Table5[[#This Row],[2026]] -> 1150 | U9: =Table57[[#This Row],[2026]]/Table57[[#This Row],[2025]] -> 1.1794872 | V9: =Table57[[#This Row],[2026]]/$T$15 -> 23.469388
B10: =Growth!B10 -> Mobile Development | C10: =Growth!N10 -> 2500000 | D10: =Capacity!F11 -> 1699056 | E10: =Collection!B15 -> 3004332.9 | F10: =E10*1.3 -> 3905632.8 | G10: =AVERAGE(C10:E10) -> 2401129.6 | H10: 2000000 | I10: =H10/12 -> 166666.67 | J10: =I10/(Table57[[#This Row],[2025]]*1.14) -> 149.94752 | K10: 1 | L10: =Growth!M10 -> 1442787.5 | M10: =L10/12 -> 120232.29 | N10: =M10*Table57[[#This Row],[%]] -> 141812.44 | P10: =Table5[[#This Row],[2022]] -> 575 | Q10: =Table5[[#This Row],[2023]] -> 625 | R10: =Table5[[#This Row],[2024]] -> 800 | S10: =Table5[[#This Row],[2025]] -> 975 | T10: =Table5[[#This Row],[2026]] -> 1150 | U10: =Table57[[#This Row],[2026]]/Table57[[#This Row],[2025]] -> 1.1794872 | V10: =Table57[[#This Row],[2026]]/$T$15 -> 23.469388
B11: =Growth!B11 -> Support Contracts | C11: =Growth!N11 -> 0 | D11: =Capacity!G11 -> 0 | E11: 0 | F11: =E11*1.3 -> 0 | G11: =AVERAGE(C11:E11) -> 0 | I11: =H11/12 -> 0 | K11: 0 | M11: =L11/12 -> 0 | N11: =M11*Table57[[#This Row],[%]] -> 0 | P11: =Table5[[#This Row],[2022]] -> 525 | Q11: =Table5[[#This Row],[2023]] -> 587.5 | R11: =Table5[[#This Row],[2024]] -> 762.5 | S11: 0 | T11: 0 | U11: 0 | V11: =Table57[[#This Row],[2026]]/$T$15 -> 0
B12: =Growth!B12 -> Websites | C12: =Growth!N12 -> 1100000 | D12: =Capacity!H11 -> 1378944 | E12: =Collection!B13 -> 1027762 | F12: =E12*1.3 -> 1336090.6 | G12: =AVERAGE(C12:E12) -> 1168902 | H12: 1100000 | I12: =H12/12 -> 91666.667 | J12: =I12/(Table57[[#This Row],[2025]]*1.14) -> 91.896408 | K12: 1 | L12: =Growth!M12 -> 694293.43 | M12: =L12/12 -> 57857.786 | N12: =M12*Table57[[#This Row],[%]] -> 69429.343 | P12: =Table5[[#This Row],[2022]] -> 475 | Q12: =Table5[[#This Row],[2023]] -> 550 | R12: =Table5[[#This Row],[2024]] -> 725 | S12: =Table5[[#This Row],[2025]] -> 875 | T12: =Table5[[#This Row],[2026]] -> 1050 | U12: =Table57[[#This Row],[2026]]/Table57[[#This Row],[2025]] -> 1.2 | V12: =Table57[[#This Row],[2026]]/$T$15 -> 21.428571
B13: Design | C13: =Growth!N13 -> 400000 | D13: =Capacity!I11 -> 474012 | E13: =Collection!B16 -> 411106.03 | F13: =E13*1.3 -> 534437.84 | G13: =AVERAGE(C13:E13) -> 428372.68 | H13: 420000 | I13: =H13/12 -> 35000 | J13: =I13/(Table57[[#This Row],[2025]]*1.14) -> 35.087719 | K13: 1 | L13: =Growth!M13 -> 314078.48 | M13: =L13/12 -> 26173.206 | N13: =M13*Table57[[#This Row],[%]] -> 31407.848 | P13: =Table5[[#This Row],[2022]] -> 0 | Q13: =Table5[[#This Row],[2023]] -> 550 | R13: =Table5[[#This Row],[2024]] -> 725 | S13: =Table5[[#This Row],[2025]] -> 875 | T13: =Table5[[#This Row],[2026]] -> 1050 | U13: =Table57[[#This Row],[2026]]/Table57[[#This Row],[2025]] -> 1.2 | V13: =Table57[[#This Row],[2026]]/$T$15 -> 21.428571
B14: =Growth!B14 -> Hosting | C14: =Growth!N14 -> 362000 | E14: =Table124[[#This Row],[Total]] -> 945997.36 | F14: =E14*1.3 -> 1229796.6 | G14: =AVERAGE(C14:E14) -> 653998.68 | H14: 380000 | I14: =H14/12 -> 31666.667 | J14: =I14/(Table57[[#This Row],[2025]]*1.14) -> 3.1573012 | K14: 0 | L14: =Growth!M14 -> 376829.19 | M14: =L14/12 -> 31402.433 | N14: =M14*Table57[[#This Row],[%]] -> 30184.788 | P14: =120*P15*1.05*1.14 -> 2243.6568 | Q14: =120*Q15*1.05*1.14 -> 3418.632 | R14: =120*R15*1.05*1.14 -> 4444.2216 | S14: =Table5[[#This Row],[2025]] -> 8797.95 | T14: =Table5[[#This Row],[2026]] -> 8456.805 | U14: =Table57[[#This Row],[2026]]/Table57[[#This Row],[2025]] -> 0.96122449 | V14: =Table57[[#This Row],[2026]]/$T$15 -> 172.58786
B15: Total | C15: =SUM(C7:C14) -> 15462000 | D15: =SUM(D7:D14) -> 15642396 | E15: =SUM(E7:E14) -> 16061897 | F15: =SUM(F7:F14) -> 20880466 | G15: =SUM(G7:G14) -> 15940097 | H15: =SUM(H7:H14) -> 15400000 | I15: =SUM(I7:I14) -> 1283333.3 | L15: =SUM(L7:L14) -> 12161578 | M15: =SUM(M7:M14) -> 1013464.8 | N15: =SUM(N7:N14) -> 1198761.4 | P15: =Table5[[#This Row],[2022]] -> 15.62 | Q15: =Table5[[#This Row],[2023]] -> 23.8 | R15: =Table5[[#This Row],[2024]] -> 30.94 | S15: 47.65 | T15: 49 | U15: =Table57[[#This Row],[2026]]/Table57[[#This Row],[2025]] -> 1.0283316 | V15: =Table57[[#This Row],[2026]]/$T$15 -> 1
H16: =H15/L15 -> 1.2662831

Sheet Personnel
B2: Aura Systems
B3: Salaries Forecast
B4: Financial Numbers in 000s of EGP
B6: Assumpltions
B7: Variable | C7: Value
B8: Social Insurance | C8: 0.08
B9: 2019 Headcount
B10: Untaxable income | C10: 12
B11: E3fa2 | C11: 13.5
B12: Health Insurance per Employee per month | C12: 0
B14: Salaries Estimates | E14: 2024
B15: Role | C15: Employee | D15: 2025 Net | E15: 2026 | F15: Hourly | G15: SI | H15: Rep | I15: Y Increase | J15: Column1 | K15: Column2 | L15: SI
B16: G&A | J16: =Table4[[#This Row],[2025 Net]]*1.25 -> 0 | K16: =Table4[[#This Row],[2025 Net]]*1.15 -> 0
B17: Admin Assistant | C17: Nermeen | D17: 19.5 | E17: 22.75 | F17: =Table4[[#This Row],[2026]]/140*1000 -> 162.5 | G17: 1.93 | H17: 1 | I17: =Table4[[#This Row],[2026]]/Table4[[#This Row],[2025 Net]]-1 -> 0.16666667 | J17: =Table4[[#This Row],[2025 Net]]*1.25 -> 24.375 | K17: =Table4[[#This Row],[2025 Net]]*1.15 -> 22.425 | L17: =((MIN(Table4[[#This Row],[2026]]*0.8,9.4)*12)-13.5)*0.2975/12 -> 2.4618125
B18: Financial Manager | C18: Fadi | D18: 40 | E18: 0 | F18: =Table4[[#This Row],[2026]]/140*1000 -> 0 | H18: 1 | I18: =Table4[[#This Row],[2026]]/Table4[[#This Row],[2025 Net]]-1 -> -1 | J18: =Table4[[#This Row],[2025 Net]]*1.25 -> 50 | K18: =Table4[[#This Row],[2025 Net]]*1.15 -> 46 | L18: =((MIN(Table4[[#This Row],[2026]]*0.8,9.4)*12)-13.5)*0.2975/12 -> -0.3346875
B19: General Manager | C19: Samer | D19: 90 | E19: 104 | F19: =Table4[[#This Row],[2026]]/140*1000 -> 742.85714 | G19: =MIN(Table4[[#This Row],[2026]],8.1)*0.2975 -> 2.40975 | H19: 1 | I19: =Table4[[#This Row],[2026]]/Table4[[#This Row],[2025 Net]]-1 -> 0.15555556 | J19: =Table4[[#This Row],[2025 Net]]*1.25 -> 112.5 | K19: =Table4[[#This Row],[2025 Net]]*1.15 -> 103.5 | L19: =((MIN(Table4[[#This Row],[2026]]*0.8,9.4)*12)-13.5)*0.2975/12 -> 2.4618125
B20: Technical Lead | C20: TBH | D20: 0 | F20: =Table4[[#This Row],[2026]]/140*1000 -> 0 | G20: =MIN(Table4[[#This Row],[2026]],8.1)*0.2975 -> 2.40975 | H20: 1 | I20: =Table4[[#This Row],[2026]]/Table4[[#This Row],[2025 Net]]-1 -> #DIV/0! | J20: =Table4[[#This Row],[2025 Net]]*1.25 -> 0 | K20: =Table4[[#This Row],[2025 Net]]*1.15 -> 0 | L20: =((MIN(Table4[[#This Row],[2026]]*0.8,9.4)*12)-13.5)*0.2975/12 -> -0.3346875
B21: Sr. Sales | C21: TBH | D21: 0 | F21: =Table4[[#This Row],[2026]]/140*1000 -> 0 | G21: =MIN(Table4[[#This Row],[2026]],8.1)*0.2975 -> 2.40975 | H21: 1 | I21: =Table4[[#This Row],[2026]]/Table4[[#This Row],[2025 Net]]-1 -> #DIV/0! | J21: =Table4[[#This Row],[2025 Net]]*1.25 -> 0 | K21: =Table4[[#This Row],[2025 Net]]*1.15 -> 0 | L21: =((MIN(Table4[[#This Row],[2026]]*0.8,9.4)*12)-13.5)*0.2975/12 -> -0.3346875
B22: Jr. Sales | D22: 0 | F22: =Table4[[#This Row],[2026]]/140*1000 -> 0 | G22: =MIN(Table4[[#This Row],[2026]],8.1)*0.2975 -> 2.40975 | H22: 1 | I22: =Table4[[#This Row],[2026]]/Table4[[#This Row],[2025 Net]]-1 -> #DIV/0! | J22: =Table4[[#This Row],[2025 Net]]*1.25 -> 0 | K22: =Table4[[#This Row],[2025 Net]]*1.15 -> 0 | L22: =((MIN(Table4[[#This Row],[2026]]*0.8,9.4)*12)-13.5)*0.2975/12 -> -0.3346875
B23: Accountant | C23: Mariam | D23: 19.5 | E23: 22.75 | F23: =Table4[[#This Row],[2026]]/140*1000 -> 162.5 | G23: 1.59 | H23: 1 | I23: =Table4[[#This Row],[2026]]/Table4[[#This Row],[2025 Net]]-1 -> 0.16666667 | J23: =Table4[[#This Row],[2025 Net]]*1.25 -> 24.375 | K23: =Table4[[#This Row],[2025 Net]]*1.15 -> 22.425 | L23: =((MIN(Table4[[#This Row],[2026]]*0.8,9.4)*12)-13.5)*0.2975/12 -> 2.4618125
B24: Office Boy | C24: Ibrahim | D24: 12.5 | E24: 14.5 | F24: =Table4[[#This Row],[2026]]/140*1000 -> 103.57143 | G24: 1.81 | H24: 1 | I24: =Table4[[#This Row],[2026]]/Table4[[#This Row],[2025 Net]]-1 -> 0.16 | J24: =Table4[[#This Row],[2025 Net]]*1.25 -> 15.625 | K24: =Table4[[#This Row],[2025 Net]]*1.15 -> 14.375 | L24: =((MIN(Table4[[#This Row],[2026]]*0.8,9.4)*12)-13.5)*0.2975/12 -> 2.4618125
B25: Custom Department | J25: =Table4[[#This Row],[2025 Net]]*1.25 -> 0 | K25: =Table4[[#This Row],[2025 Net]]*1.15 -> 0 | L25: =((MIN(Table4[[#This Row],[2026]]*0.8,9.4)*12)-13.5)*0.2975/12 -> -0.3346875
B26: Engineering Manager | C26: =C19 -> Samer | D26: =D19 -> 90 | E26: =E19 -> 104 | F26: =Table4[[#This Row],[2026]]/140*1000 -> 742.85714 | G26: =MIN(Table4[[#This Row],[2026]],8.1)*0.2975 -> 2.40975 | H26: 1 | I26: =Table4[[#This Row],[2026]]/Table4[[#This Row],[2025 Net]]-1 -> 0.15555556 | J26: =Table4[[#This Row],[2025 Net]]*1.25 -> 112.5 | K26: =Table4[[#This Row],[2025 Net]]*1.15 -> 103.5 | L26: =((MIN(Table4[[#This Row],[2026]]*0.8,9.4)*12)-13.5)*0.2975/12 -> 2.4618125
B27: Mobile Manager | C27: Fadi | D27: =D18 -> 40 | E27: =E18 -> 0 | F27: =Table4[[#This Row],[2026]]/140*1000 -> 0 | G27: =MIN(Table4[[#This Row],[2026]],8.1)*0.2975 -> 0 | H27: 1 | I27: =Table4[[#This Row],[2026]]/Table4[[#This Row],[2025 Net]]-1 -> -1 | J27: =Table4[[#This Row],[2025 Net]]*1.25 -> 50 | K27: =Table4[[#This Row],[2025 Net]]*1.15 -> 46 | L27: =((MIN(Table4[[#This Row],[2026]]*0.8,9.4)*12)-13.5)*0.2975/12 -> -0.3346875
B28: Project Manager | C28: Nathalie | D28: 30 | E28: 35 | F28: =Table4[[#This Row],[2026]]/140*1000 -> 250 | G28: =MIN(Table4[[#This Row],[2026]],8.1)*0.2975 -> 2.40975 | H28: 1 | I28: =Table4[[#This Row],[2026]]/Table4[[#This Row],[2025 Net]]-1 -> 0.16666667 | J28: =Table4[[#This Row],[2025 Net]]*1.25 -> 37.5 | K28: =Table4[[#This Row],[2025 Net]]*1.15 -> 34.5 | L28: =((MIN(Table4[[#This Row],[2026]]*0.8,9.4)*12)-13.5)*0.2975/12 -> 2.4618125
B29: Backend Developer 1 | C29: Hazem | D29: 38 | E29: 44 | F29: =Table4[[#This Row],[2026]]/140*1000 -> 314.28571 | G29: =MIN(Table4[[#This Row],[2026]],8.1)*0.2975 -> 2.40975 | H29: 1 | I29: =Table4[[#This Row],[2026]]/Table4[[#This Row],[2025 Net]]-1 -> 0.15789474 | J29: =Table4[[#This Row],[2025 Net]]*1.25 -> 47.5 | K29: =Table4[[#This Row],[2025 Net]]*1.15 -> 43.7 | L29: =((MIN(Table4[[#This Row],[2026]]*0.8,9.4)*12)-13.5)*0.2975/12 -> 2.4618125
B30: Backend Developer 2 | C30: TBH | D30: 18 | E30: 21 | F30: =Table4[[#This Row],[2026]]/140*1000 -> 150 | G30: 1.81 | H30: 1 | I30: =Table4[[#This Row],[2026]]/Table4[[#This Row],[2025 Net]]-1 -> 0.16666667 | J30: =Table4[[#This Row],[2025 Net]]*1.25 -> 22.5 | K30: =Table4[[#This Row],[2025 Net]]*1.15 -> 20.7 | L30: =((MIN(Table4[[#This Row],[2026]]*0.8,9.4)*12)-13.5)*0.2975/12 -> 2.4618125
B31: Backend Developer 3 | C31: Mostafa | D31: 19 | E31: 21 | F31: =Table4[[#This Row],[2026]]/140*1000 -> 150 | G31: 1.59 | H31: 1 | I31: =Table4[[#This Row],[2026]]/Table4[[#This Row],[2025 Net]]-1 -> 0.10526316 | J31: =Table4[[#This Row],[2025 Net]]*1.25 -> 23.75 | K31: =Table4[[#This Row],[2025 Net]]*1.15 -> 21.85 | L31: =((MIN(Table4[[#This Row],[2026]]*0.8,9.4)*12)-13.5)*0.2975/12 -> 2.4618125
B32: Backend Developer 4 | C32: Shady | D32: 34 | E32: 40 | F32: =Table4[[#This Row],[2026]]/140*1000 -> 285.71429 | G32: =MIN(Table4[[#This Row],[2026]],8.1)*0.2975 -> 2.40975 | H32: 1 | I32: =Table4[[#This Row],[2026]]/Table4[[#This Row],[2025 Net]]-1 -> 0.17647059 | J32: =Table4[[#This Row],[2025 Net]]*1.25 -> 42.5 | K32: =Table4[[#This Row],[2025 Net]]*1.15 -> 39.1 | L32: =((MIN(Table4[[#This Row],[2026]]*0.8,9.4)*12)-13.5)*0.2975/12 -> 2.4618125
B33: Backend Developer 5 | C33: TBH | D33: 17 | E33: 19.5 | F33: =Table4[[#This Row],[2026]]/140*1000 -> 139.28571 | G33: 1.81 | H33: 1 | I33: =Table4[[#This Row],[2026]]/Table4[[#This Row],[2025 Net]]-1 -> 0.14705882 | J33: =Table4[[#This Row],[2025 Net]]*1.25 -> 21.25 | K33: =Table4[[#This Row],[2025 Net]]*1.15 -> 19.55 | L33: =((MIN(Table4[[#This Row],[2026]]*0.8,9.4)*12)-13.5)*0.2975/12 -> 2.4618125
B34: Project Manager | C34: TBH | D34: 18 | E34: 23 | F34: =Table4[[#This Row],[2026]]/140*1000 -> 164.28571 | G34: 1.71 | H34: 1 | I34: =Table4[[#This Row],[2026]]/Table4[[#This Row],[2025 Net]]-1 -> 0.27777778 | J34: =Table4[[#This Row],[2025 Net]]*1.25 -> 22.5 | K34: =Table4[[#This Row],[2025 Net]]*1.15 -> 20.7 | L34: =((MIN(Table4[[#This Row],[2026]]*0.8,9.4)*12)-13.5)*0.2975/12 -> 2.4618125
B35: Mobile Developer 1 | C35: Mina | D35: 25 | E35: 31 | F35: =Table4[[#This Row],[2026]]/140*1000 -> 221.42857 | G35: 2.28 | H35: 1 | I35: =Table4[[#This Row],[2026]]/Table4[[#This Row],[2025 Net]]-1 -> 0.24 | J35: =Table4[[#This Row],[2025 Net]]*1.25 -> 31.25 | K35: =Table4[[#This Row],[2025 Net]]*1.15 -> 28.75 | L35: =((MIN(Table4[[#This Row],[2026]]*0.8,9.4)*12)-13.5)*0.2975/12 -> 2.4618125
B36: Mobile Developer 2 | C36: TBH | D36: 18 | E36: 21 | F36: =Table4[[#This Row],[2026]]/140*1000 -> 150 | G36: =MIN(Table4[[#This Row],[2026]],8.1)*0.2975 -> 2.40975 | H36: 1 | I36: =Table4[[#This Row],[2026]]/Table4[[#This Row],[2025 Net]]-1 -> 0.16666667 | J36: =Table4[[#This Row],[2025 Net]]*1.25 -> 22.5 | K36: =Table4[[#This Row],[2025 Net]]*1.15 -> 20.7 | L36: =((MIN(Table4[[#This Row],[2026]]*0.8,9.4)*12)-13.5)*0.2975/12 -> 2.4618125
B37: Tester | C37: Monad | D37: 14 | E37: 17 | F37: =Table4[[#This Row],[2026]]/140*1000 -> 121.42857 | G37: 1.57 | H37: 1 | I37: =Table4[[#This Row],[2026]]/Table4[[#This Row],[2025 Net]]-1 -> 0.21428571 | J37: =Table4[[#This Row],[2025 Net]]*1.25 -> 17.5 | K37: =Table4[[#This Row],[2025 Net]]*1.15 -> 16.1 | L37: =((MIN(Table4[[#This Row],[2026]]*0.8,9.4)*12)-13.5)*0.2975/12 -> 2.4618125
B38: Tester | C38: Anton | D38: 17 | E38: 20 | F38: =Table4[[#This Row],[2026]]/140*1000 -> 142.85714 | G38: =1.57*0.6 -> 0.942 | H38: 1 | I38: =Table4[[#This Row],[2026]]/Table4[[#This Row],[2025 Net]]-1 -> 0.17647059 | J38: =Table4[[#This Row],[2025 Net]]*1.25 -> 21.25 | K38: =Table4[[#This Row],[2025 Net]]*1.15 -> 19.55 | L38: =((MIN(Table4[[#This Row],[2026]]*0.8,9.4)*12)-13.5)*0.2975/12 -> 2.4618125
B39: Websites Department | J39: =Table4[[#This Row],[2025 Net]]*1.25 -> 0 | K39: =Table4[[#This Row],[2025 Net]]*1.15 -> 0 | L39: =((MIN(Table4[[#This Row],[2026]]*0.8,9.4)*12)-13.5)*0.2975/12 -> -0.3346875
B40: =B26 -> Engineering Manager | C40: =C26 -> Samer | D40: =D19 -> 90 | E40: =E19 -> 104 | F40: =Table4[[#This Row],[2026]]/140*1000 -> 742.85714 | H40: 1 | I40: =Table4[[#This Row],[2026]]/Table4[[#This Row],[2025 Net]]-1 -> 0.15555556 | J40: =Table4[[#This Row],[2025 Net]]*1.25 -> 112.5 | K40: =Table4[[#This Row],[2025 Net]]*1.15 -> 103.5 | L40: =((MIN(Table4[[#This Row],[2026]]*0.8,9.4)*12)-13.5)*0.2975/12 -> 2.4618125
B41: =B28 -> Project Manager | C41: =C28 -> Nathalie | D41: =D28 -> 30 | E41: =E28 -> 35 | F41: =Table4[[#This Row],[2026]]/140*1000 -> 250 | H41: 1 | I41: =Table4[[#This Row],[2026]]/Table4[[#This Row],[2025 Net]]-1 -> 0.16666667 | J41: =Table4[[#This Row],[2025 Net]]*1.25 -> 37.5 | K41: =Table4[[#This Row],[2025 Net]]*1.15 -> 34.5 | L41: =((MIN(Table4[[#This Row],[2026]]*0.8,9.4)*12)-13.5)*0.2975/12 -> 2.4618125
B42: Frontend Designer | C42: Esraa | D42: 20 | E42: 23.5 | F42: =Table4[[#This Row],[2026]]/140*1000 -> 167.85714 | G42: 1.69 | H42: 1 | I42: =Table4[[#This Row],[2026]]/Table4[[#This Row],[2025 Net]]-1 -> 0.175 | J42: =Table4[[#This Row],[2025 Net]]*1.25 -> 25 | K42: =Table4[[#This Row],[2025 Net]]*1.15 -> 23 | L42: =((MIN(Table4[[#This Row],[2026]]*0.8,9.4)*12)-13.5)*0.2975/12 -> 2.4618125
B43: Frontend Developer 1 | C43: Mohamed | D43: 23 | E43: 27 | F43: =Table4[[#This Row],[2026]]/140*1000 -> 192.85714 | G43: =MIN(Table4[[#This Row],[2026]],8.1)*0.2975 -> 2.40975 | H43: 1 | I43: =Table4[[#This Row],[2026]]/Table4[[#This Row],[2025 Net]]-1 -> 0.17391304 | J43: =Table4[[#This Row],[2025 Net]]*1.25 -> 28.75 | K43: =Table4[[#This Row],[2025 Net]]*1.15 -> 26.45 | L43: =((MIN(Table4[[#This Row],[2026]]*0.8,9.4)*12)-13.5)*0.2975/12 -> 2.4618125
B44: Frontend Developer 2 | C44: kirolos | D44: 15 | E44: 17.5 | F44: =Table4[[#This Row],[2026]]/140*1000 -> 125 | G44: =1.81*0.8 -> 1.448 | H44: 1 | I44: =Table4[[#This Row],[2026]]/Table4[[#This Row],[2025 Net]]-1 -> 0.16666667 | J44: =Table4[[#This Row],[2025 Net]]*1.25 -> 18.75 | K44: =Table4[[#This Row],[2025 Net]]*1.15 -> 17.25 | L44: =((MIN(Table4[[#This Row],[2026]]*0.8,9.4)*12)-13.5)*0.2975/12 -> 2.4618125
B45: Frontend Developer 3 | F45: =Table4[[#This Row],[2026]]/140*1000 -> 0 | H45: 1 | J45: =Table4[[#This Row],[2025 Net]]*1.25 -> 0 | K45: =Table4[[#This Row],[2025 Net]]*1.15 -> 0 | L45: =((MIN(Table4[[#This Row],[2026]]*0.8,9.4)*12)-13.5)*0.2975/12 -> -0.3346875
B46: Tester | C46: =C37 -> Monad | D46: =D37 -> 14 | E46: =E37 -> 17 | F46: =Table4[[#This Row],[2026]]/140*1000 -> 121.42857 | H46: 1 | I46: =Table4[[#This Row],[2026]]/Table4[[#This Row],[2025 Net]]-1 -> 0.21428571 | J46: =Table4[[#This Row],[2025 Net]]*1.25 -> 17.5 | K46: =Table4[[#This Row],[2025 Net]]*1.15 -> 16.1 | L46: =((MIN(Table4[[#This Row],[2026]]*0.8,9.4)*12)-13.5)*0.2975/12 -> 2.4618125
B47: =B38 -> Tester | C47: Anton | D47: 17 | E47: =E38 -> 20 | F47: =Table4[[#This Row],[2026]]/140*1000 -> 142.85714 | H47: 1 | I47: =Table4[[#This Row],[2026]]/Table4[[#This Row],[2025 Net]]-1 -> 0.17647059 | J47: =Table4[[#This Row],[2025 Net]]*1.25 -> 21.25 | K47: =Table4[[#This Row],[2025 Net]]*1.15 -> 19.55 | L47: =((MIN(Table4[[#This Row],[2026]]*0.8,9.4)*12)-13.5)*0.2975/12 -> 2.4618125
B48: .NET | J48: =Table4[[#This Row],[2025 Net]]*1.25 -> 0 | K48: =Table4[[#This Row],[2025 Net]]*1.15 -> 0 | L48: =((MIN(Table4[[#This Row],[2026]]*0.8,9.4)*12)-13.5)*0.2975/12 -> -0.3346875
B49: Engineering Manager | C49: Samer | D49: =D19 -> 90 | E49: =E19 -> 104 | F49: =Table4[[#This Row],[2026]]/140*1000 -> 742.85714 | H49: 1 | I49: =Table4[[#This Row],[2026]]/Table4[[#This Row],[2025 Net]]-1 -> 0.15555556 | J49: =Table4[[#This Row],[2025 Net]]*1.25 -> 112.5 | K49: =Table4[[#This Row],[2025 Net]]*1.15 -> 103.5 | L49: =((MIN(Table4[[#This Row],[2026]]*0.8,9.4)*12)-13.5)*0.2975/12 -> 2.4618125
B50: Sr. Software Developer | C50: Najah | D50: 38 | E50: 44 | F50: =Table4[[#This Row],[2026]]/140*1000 -> 314.28571 | G50: =MIN(Table4[[#This Row],[2026]],8.1)*0.2975 -> 2.40975 | H50: 1 | I50: =Table4[[#This Row],[2026]]/Table4[[#This Row],[2025 Net]]-1 -> 0.15789474 | J50: =Table4[[#This Row],[2025 Net]]*1.25 -> 47.5 | K50: =Table4[[#This Row],[2025 Net]]*1.15 -> 43.7 | L50: =((MIN(Table4[[#This Row],[2026]]*0.8,9.4)*12)-13.5)*0.2975/12 -> 2.4618125
B51: Jr. Software Developer | C51: Eslam | D51: 13 | E51: 18 | F51: =Table4[[#This Row],[2026]]/140*1000 -> 128.57143 | G51: =MIN(Table4[[#This Row],[2026]],8.1)*0.2975 -> 2.40975 | H51: 1 | I51: =Table4[[#This Row],[2026]]/Table4[[#This Row],[2025 Net]]-1 -> 0.38461538 | J51: =Table4[[#This Row],[2025 Net]]*1.25 -> 16.25 | K51: =Table4[[#This Row],[2025 Net]]*1.15 -> 14.95 | L51: =((MIN(Table4[[#This Row],[2026]]*0.8,9.4)*12)-13.5)*0.2975/12 -> 2.4618125
B52: Jr. Software Developer | C52: Reem | D52: 17 | E52: 19.75 | F52: =Table4[[#This Row],[2026]]/140*1000 -> 141.07143 | G52: =MIN(Table4[[#This Row],[2026]],8.1)*0.2975 -> 2.40975 | H52: 1 | I52: =Table4[[#This Row],[2026]]/Table4[[#This Row],[2025 Net]]-1 -> 0.16176471 | J52: =Table4[[#This Row],[2025 Net]]*1.25 -> 21.25 | K52: =Table4[[#This Row],[2025 Net]]*1.15 -> 19.55 | L52: =((MIN(Table4[[#This Row],[2026]]*0.8,9.4)*12)-13.5)*0.2975/12 -> 2.4618125
B53: Project Manager | D53: 18 | E53: =E34 -> 23 | F53: =Table4[[#This Row],[2026]]/140*1000 -> 164.28571 | G53: =MIN(Table4[[#This Row],[2026]],8.1)*0.2975 -> 2.40975 | H53: 1 | I53: =Table4[[#This Row],[2026]]/Table4[[#This Row],[2025 Net]]-1 -> 0.27777778 | J53: =Table4[[#This Row],[2025 Net]]*1.25 -> 22.5 | K53: =Table4[[#This Row],[2025 Net]]*1.15 -> 20.7 | L53: =((MIN(Table4[[#This Row],[2026]]*0.8,9.4)*12)-13.5)*0.2975/12 -> 2.4618125
B54: Business Analyst/Documentation | D54: 18 | E54: 21 | F54: =Table4[[#This Row],[2026]]/140*1000 -> 150 | G54: =MIN(Table4[[#This Row],[2026]],8.1)*0.2975 -> 2.40975 | H54: 1 | I54: =Table4[[#This Row],[2026]]/Table4[[#This Row],[2025 Net]]-1 -> 0.16666667 | J54: =Table4[[#This Row],[2025 Net]]*1.25 -> 22.5 | K54: =Table4[[#This Row],[2025 Net]]*1.15 -> 20.7 | L54: =((MIN(Table4[[#This Row],[2026]]*0.8,9.4)*12)-13.5)*0.2975/12 -> 2.4618125
B55: Tester | C55: Anton | D55: 17 | E55: =E47 -> 20 | F55: =Table4[[#This Row],[2026]]/140*1000 -> 142.85714 | G55: =MIN(Table4[[#This Row],[2026]],8.1)*0.2975 -> 2.40975 | H55: 1 | I55: =Table4[[#This Row],[2026]]/Table4[[#This Row],[2025 Net]]-1 -> 0.17647059 | J55: =Table4[[#This Row],[2025 Net]]*1.25 -> 21.25 | K55: =Table4[[#This Row],[2025 Net]]*1.15 -> 19.55 | L55: =((MIN(Table4[[#This Row],[2026]]*0.8,9.4)*12)-13.5)*0.2975/12 -> 2.4618125
B57: Headcount Forecast
C58: 46023 | D58: 46054 | E58: 46082 | F58: 46113 | G58: 46143 | H58: 46174 | I58: 46204 | J58: 46235 | K58: 46266 | L58: 46296 | M58: 46327 | N58: 46357
B59: =B16 -> G&A
B60: =B17 -> Admin Assistant | C60: 1 | D60: 1 | E60: 1 | F60: 1 | G60: 1 | H60: 1 | I60: 1 | J60: 1 | K60: 1 | L60: 1 | M60: 1 | N60: 1
B61: =B18 -> Financial Manager | C61: 0 | D61: 0 | E61: 0 | F61: 0 | G61: 0 | H61: 0 | I61: 0 | J61: 0 | K61: 0 | L61: 0 | M61: 0 | N61: 0
B62: =B19 -> General Manager | C62: 0.3 | D62: 0.3 | E62: 0.3 | F62: 0.3 | G62: 0.3 | H62: 0.3 | I62: 0.3 | J62: 0.3 | K62: 0.3 | L62: 0.3 | M62: 0.3 | N62: 0.3
B63: =B20 -> Technical Lead | C63: 0 | D63: 0 | E63: 0 | F63: 0 | G63: 0 | H63: 0 | I63: 0 | J63: 0 | K63: 0 | L63: 0 | M63: 0 | N63: 0
B64: =B21 -> Sr. Sales | C64: 0 | D64: 0 | E64: 0 | F64: 0 | G64: 0 | H64: 0 | I64: 0 | J64: 0 | K64: 0 | L64: 0 | M64: 0 | N64: 0
B65: =B22 -> Jr. Sales | C65: 0 | D65: 0 | E65: 0 | F65: 0 | G65: 0 | H65: 0 | I65: 0 | J65: 0 | K65: 0 | L65: 0 | M65: 0 | N65: 0
B66: =B23 -> Accountant | C66: 1 | D66: 1 | E66: 1 | F66: 1 | G66: 1 | H66: 1 | I66: 1 | J66: 1 | K66: 1 | L66: 1 | M66: 1 | N66: 1
B67: =B24 -> Office Boy | C67: 1 | D67: 1 | E67: 1 | F67: 1 | G67: 1 | H67: 1 | I67: 1 | J67: 1 | K67: 1 | L67: 1 | M67: 1 | N67: 1
B68: G&A Headcount | C68: =SUM(C60:C67) -> 3.3 | D68: =SUM(D60:D67) -> 3.3 | E68: =SUM(E60:E67) -> 3.3 | F68: =SUM(F60:F67) -> 3.3 | G68: =SUM(G60:G67) -> 3.3 | H68: =SUM(H60:H67) -> 3.3 | I68: =SUM(I60:I67) -> 3.3 | J68: =SUM(J60:J67) -> 3.3 | ... N68: =SUM(N60:N67) -> 3.3 | O68: =AVERAGE(C68:N68) -> 3.3
B69: =B25 -> Custom Department
B70: =B26 -> Engineering Manager | C70: 0.25 | D70: 0.25 | E70: 0.25 | F70: 0.25 | G70: 0.25 | H70: 0.25 | I70: 0.25 | J70: 0.25 | K70: 0.25 | L70: 0.25 | M70: 0.25 | N70: 0.25
B71: =B27 -> Mobile Manager | Q71: =SUM(C70:N82)+SUM(C85:N92) -> 119.4
B72: =B28 -> Project Manager | C72: 0.5 | D72: 0.5 | E72: 0.5 | F72: 0.5 | G72: 0.5 | H72: 0.5 | I72: 0.5 | J72: 0.5 | K72: 0.5 | L72: 0.5 | M72: 0.5 | N72: 0.5
B73: =B29 -> Backend Developer 1 | C73: 1 | D73: 1 | E73: 1 | F73: 1 | G73: 1 | H73: 1 | I73: 1 | J73: 1 | K73: 1 | L73: 1 | M73: 1 | N73: 1
B74: =B30 -> Backend Developer 2 | C74: 0 | D74: 0 | E74: 0 | F74: 0 | G74: 0 | H74: 0 | I74: 0 | J74: 0 | K74: 0 | L74: 0 | M74: 0 | N74: 0
B75: =B31 -> Backend Developer 3 | C75: 1 | D75: 1 | E75: 1 | F75: 1 | G75: 1 | H75: 1 | I75: 1 | J75: 1 | K75: 1 | L75: 1 | M75: 1 | N75: 1
B76: =B32 -> Backend Developer 4 | C76: 1 | D76: 1 | E76: 1 | F76: 1 | G76: 1 | H76: 1 | I76: 1 | J76: 1 | K76: 1 | L76: 1 | M76: 1 | N76: 1
B77: =B33 -> Backend Developer 5 | C77: 0 | D77: 0 | E77: 0 | F77: 0 | G77: 0 | H77: 0 | I77: 0 | J77: 0 | K77: 0 | L77: 0 | M77: 0 | N77: 0
B78: =B34 -> Project Manager | C78: 0 | D78: 0 | E78: 0 | F78: 0 | G78: 0 | H78: 0 | I78: 0 | J78: 0 | K78: 0 | L78: 0 | M78: 0 | N78: 0
B79: =B35 -> Mobile Developer 1 | C79: 1 | D79: 1 | E79: 1 | F79: 1 | G79: 1 | H79: 1 | I79: 1 | J79: 1 | K79: 1 | L79: 1 | M79: 1 | N79: 1
B80: =B36 -> Mobile Developer 2 | C80: 0 | D80: 0 | E80: 0 | F80: 0 | G80: 0 | H80: 0 | I80: 0 | J80: 0 | K80: 0 | L80: 0 | M80: 0 | N80: 0
B81: =B37 -> Tester | C81: 0.5 | D81: 0.5 | E81: 0.5 | F81: 0.5 | G81: 0.5 | H81: 0.5 | I81: 0.5 | J81: 0.5 | K81: 0.5 | L81: 0.5 | M81: 0.5 | N81: 0.5
B82: =B38 -> Tester | C82: 0.25 | D82: 0.25 | E82: 0.25 | F82: 0.25 | G82: 0.25 | H82: 0.25 | I82: 0.25 | J82: 0.25 | K82: 0.25 | L82: 0.25 | M82: 0.25 | N82: 0.25
B83: Software Department Headcount | C83: =SUM(C70:C82) -> 5.5 | D83: =SUM(D70:D82) -> 5.5 | E83: =SUM(E70:E82) -> 5.5 | F83: =SUM(F70:F82) -> 5.5 | G83: =SUM(G70:G82) -> 5.5 | H83: =SUM(H70:H82) -> 5.5 | I83: =SUM(I70:I82) -> 5.5 | J83: =SUM(J70:J82) -> 5.5 | ... N83: =SUM(N70:N82) -> 5.5 | O83: =AVERAGE(C83:N83) -> 5.5
B84: =B39 -> Websites Department
B85: =B40 -> Engineering Manager | C85: 0.2 | D85: 0.2 | E85: 0.2 | F85: 0.2 | G85: 0.2 | H85: 0.2 | I85: 0.2 | J85: 0.2 | K85: 0.2 | L85: 0.2 | M85: 0.2 | N85: 0.2
B86: =B41 -> Project Manager | C86: 0.5 | D86: 0.5 | E86: 0.5 | F86: 0.5 | G86: 0.5 | H86: 0.5 | I86: 0.5 | J86: 0.5 | K86: 0.5 | L86: 0.5 | M86: 0.5 | N86: 0.5
B87: =B42 -> Frontend Designer | C87: 1 | D87: 1 | E87: 1 | F87: 1 | G87: 1 | H87: 1 | I87: 1 | J87: 1 | K87: 1 | L87: 1 | M87: 1 | N87: 1
B88: =B43 -> Frontend Developer 1 | C88: 1 | D88: 1 | E88: 1 | F88: 1 | G88: 1 | H88: 1 | I88: 1 | J88: 1 | K88: 1 | L88: 1 | M88: 1 | N88: 1
B89: =B44 -> Frontend Developer 2 | C89: 1 | D89: 1 | E89: 1 | F89: 1 | G89: 1 | H89: 1 | I89: 1 | J89: 1 | K89: 1 | L89: 1 | M89: 1 | N89: 1
B90: =B45 -> Frontend Developer 3
B91: =B46 -> Tester | C91: 0.5 | D91: 0.5 | E91: 0.5 | F91: 0.5 | G91: 0.5 | H91: 0.5 | I91: 0.5 | J91: 0.5 | K91: 0.5 | L91: 0.5 | M91: 0.5 | N91: 0.5
B92: =B47 -> Tester | C92: =C82 -> 0.25 | D92: =D82 -> 0.25 | E92: =E82 -> 0.25 | F92: =F82 -> 0.25 | G92: =G82 -> 0.25 | H92: =H82 -> 0.25 | I92: =I82 -> 0.25 | J92: =J82 -> 0.25 | ... N92: =N82 -> 0.25
B93: Websites Department Headcount | C93: =SUM(C85:C92) -> 4.45 | D93: =SUM(D85:D92) -> 4.45 | E93: =SUM(E85:E92) -> 4.45 | F93: =SUM(F85:F92) -> 4.45 | G93: =SUM(G85:G92) -> 4.45 | H93: =SUM(H85:H92) -> 4.45 | I93: =SUM(I85:I92) -> 4.45 | J93: =SUM(J85:J92) -> 4.45 | ... N93: =SUM(N85:N92) -> 4.45 | O93: =AVERAGE(C93:N93) -> 4.45
B94: .Net
B95: Engineering Manager | C95: 0.25 | D95: 0.25 | E95: 0.25 | F95: 0.25 | G95: 0.25 | H95: 0.25 | I95: 0.25 | J95: 0.25 | K95: 0.25 | L95: 0.25 | M95: 0.25 | N95: 0.25
B96: Sr. Software Developer | C96: 1 | D96: 1 | E96: 1 | F96: 1 | G96: 1 | H96: 1 | I96: 1 | J96: 1 | K96: 1 | L96: 1 | M96: 1 | N96: 1
B97: Jr. Software Developer | C97: 1 | D97: 1 | E97: 1 | F97: 1 | G97: 1 | H97: 1 | I97: 1 | J97: 1 | K97: 1 | L97: 1 | M97: 1 | N97: 1
B98: Jr. Software Developer | C98: 1 | D98: 1 | E98: 1 | F98: 1 | G98: 1 | H98: 1 | I98: 1 | J98: 1 | K98: 1 | L98: 1 | M98: 1 | N98: 1
B99: Project Manager | C99: 0 | D99: 0 | E99: 0 | F99: 0 | G99: 0 | H99: 0 | I99: 0 | J99: 0 | K99: 0 | L99: 0 | M99: 0 | N99: 0
B100: =B54 -> Business Analyst/Documentation | C100: 0 | D100: 0 | E100: 0 | F100: 0 | G100: 0 | H100: 0 | I100: 0 | J100: 0 | K100: 0 | L100: 0 | M100: 0 | N100: 0 | O100: =SUM(C109:N109) -> 273
B101: Tester | C101: 0.5 | D101: 0.5 | E101: 0.5 | F101: 0.5 | G101: 0.5 | H101: 0.5 | I101: 0.5 | J101: 0.5 | K101: 0.5 | L101: 0.5 | M101: 0.5 | N101: 0.5 | O101: =SUM(C110:N110) -> 0
B102: .Net Department Headcount | C102: =SUM(C94:C101) -> 3.75 | D102: =SUM(D94:D101) -> 3.75 | E102: =SUM(E94:E101) -> 3.75 | F102: =SUM(F94:F101) -> 3.75 | G102: =SUM(G94:G101) -> 3.75 | H102: =SUM(H94:H101) -> 3.75 | I102: =SUM(I94:I101) -> 3.75 | J102: =SUM(J94:J101) -> 3.75 | ... N102: =SUM(N94:N101) -> 3.75 | O102: =AVERAGE(C102:N102) -> 3.75
B103: Total Headcount | C103: =C68+C83+C93+C102 -> 17 | D103: =D68+D83+D93+D102 -> 17 | E103: =E68+E83+E93+E102 -> 17 | F103: =F68+F83+F93+F102 -> 17 | G103: =G68+G83+G93+G102 -> 17 | H103: =H68+H83+H93+H102 -> 17 | I103: =I68+I83+I93+I102 -> 17 | J103: =J68+J83+J93+J102 -> 17 | ... N103: =N68+N83+N93+N102 -> 17 | O103: =AVERAGE(C103:N103) -> 17
B105: Salaries Forecast
...

Sheet OpEx
B2: Aura Systems
B3: OPEX (Other) Forecast
B4: Financial Numbers in 000s of EGP
B6: Inflation | C6: 0.1
B8: OPEX Estimates
B9: Opex item | C9: Cost/Month | D9: Rep | E9: 2025
B10: =[11]OpEx!$B7 -> Rent | C10: =E10*1.1 -> 19965 | D10: 1 | E10: 18150
B11: =[11]OpEx!$B8 -> Consumables | C11: =E11*1.1 -> 7935.9335 | D11: 1 | E11: =AVERAGE([12]OpEx!$C$8:$L$8) -> 7214.485
B12: =[11]OpEx!$B9 -> Office Supplies | C12: =E12*1.1 -> 204.38 | D12: 1 | E12: =AVERAGE([12]OpEx!$C$9:$L$9) -> 185.8
B13: =[11]OpEx!$B10 -> Services | C13: =E13*1.1 -> 794.2 | D13: 1 | E13: =AVERAGE([12]OpEx!$C$10:$L$10) -> 722
B14: =[11]OpEx!$B11 -> Bills | C14: =E14*1.1 -> 660 | D14: 1 | E14: =AVERAGE([12]OpEx!$C$11:$L$11) -> 600
B15: =[11]OpEx!$B12 -> Internet | C15: =E15*1.1 -> 2244.1738 | D15: 1 | E15: =AVERAGE([12]OpEx!$C$12:$L$12) -> 2040.158
B16: =[11]OpEx!$B13 -> Subscriptions | C16: =E16*1.1 -> 44287.868 | D16: 1 | E16: =AVERAGE([12]OpEx!$C$13:$L$13) -> 40261.698
B17: =[11]OpEx!$B14 -> Utilities | C17: =E17*1.1 -> 1935.1354 | D17: 1 | E17: =AVERAGE([12]OpEx!$C$14:$L$14) -> 1759.214
B18: =[11]OpEx!$B15 -> Transportation | C18: =E18*1.1 -> 525.03 | D18: 1 | E18: =AVERAGE([12]OpEx!$C$15:$L$15) -> 477.3
B19: =[11]OpEx!$B16 -> Bank Charges | C19: =E19*1.1 -> 1710.3458 | D19: 1 | E19: =AVERAGE([12]OpEx!$C$16:$L$16) -> 1554.8598
B20: =[11]OpEx!$B17 -> Marketing | C20: =E20*1.1 -> 0 | D20: 1 | E20: =AVERAGE([12]OpEx!$C$17:$L$17) -> 0
B21: =[11]OpEx!$B18 -> Medical | C21: =E21*1.1 -> 9776.8 | D21: 1 | E21: =AVERAGE([12]OpEx!$C$18:$L$18) -> 8888
B22: =[11]OpEx!$B19 -> Courses | C22: =E22*1.1 -> 0 | D22: 1 | E22: =AVERAGE([12]OpEx!$C$19:$L$19) -> 0
B24: OPEX Forecast
C25: 46023 | D25: 46054 | E25: 46082 | F25: 46113 | G25: 46143 | H25: 46174 | I25: 46204 | J25: 46235 | K25: 46266 | L25: 46296 | M25: 46327 | N25: 46357
B26: =B10 -> Rent | C26: 3 | D26: 0 | E26: 0 | F26: 3 | G26: 0 | H26: 0 | I26: 3 | J26: 0 | K26: 0 | L26: 3 | M26: 0 | N26: 0
B27: =B11 -> Consumables | C27: 1 | D27: 1 | E27: 1 | F27: 1 | G27: 1 | H27: 1 | I27: 1 | J27: 1 | K27: 1 | L27: 1 | M27: 1 | N27: 1
B28: =B12 -> Office Supplies | C28: 1 | D28: 1 | E28: 1 | F28: 1 | G28: 1 | H28: 1 | I28: 1 | J28: 1 | K28: 1 | L28: 1 | M28: 1 | N28: 1
B29: =B13 -> Services | C29: 1 | D29: 1 | E29: 1 | F29: 1 | G29: 1 | H29: 1 | I29: 1 | J29: 1 | K29: 1 | L29: 1 | M29: 1 | N29: 1
B30: =B14 -> Bills | C30: 1 | D30: 1 | E30: 1 | F30: 1 | G30: 1 | H30: 1 | I30: 1 | J30: 1 | K30: 1 | L30: 1 | M30: 1 | N30: 1
B31: =B15 -> Internet | C31: 1 | D31: 1 | E31: 1 | F31: 1 | G31: 1 | H31: 1 | I31: 1 | J31: 1 | K31: 1 | L31: 1 | M31: 1 | N31: 1
B32: =B16 -> Subscriptions | C32: 1 | D32: 1 | E32: 1 | F32: 1 | G32: 1 | H32: 1 | I32: 1 | J32: 1 | K32: 1 | L32: 1 | M32: 1 | N32: 1
B33: =B17 -> Utilities | C33: 1 | D33: 1 | E33: 1 | F33: 1 | G33: 1 | H33: 1 | I33: 1 | J33: 1 | K33: 1 | L33: 1 | M33: 1 | N33: 1
B34: =B18 -> Transportation | C34: 1 | D34: 1 | E34: 1 | F34: 1 | G34: 1 | H34: 1 | I34: 1 | J34: 1 | K34: 1 | L34: 1 | M34: 1 | N34: 1
B35: =B19 -> Bank Charges | C35: 1 | D35: 1 | E35: 1 | F35: 1 | G35: 1 | H35: 1 | I35: 1 | J35: 1 | K35: 1 | L35: 1 | M35: 1 | N35: 1
B36: =B20 -> Marketing | C36: 1 | D36: 1 | E36: 1 | F36: 1 | G36: 1 | H36: 1 | I36: 1 | J36: 1 | K36: 1 | L36: 1 | M36: 1 | N36: 1
B37: =B21 -> Medical | C37: 1 | D37: 1 | E37: 1 | F37: 1 | G37: 1 | H37: 1 | I37: 1 | J37: 1 | K37: 1 | L37: 1 | M37: 1 | N37: 1
B38: =B22 -> Courses | C38: 1 | D38: 1 | E38: 1 | F38: 1 | G38: 1 | H38: 1 | I38: 1 | J38: 1 | K38: 1 | L38: 1 | M38: 1 | N38: 1
B40: OPEX Expense
C41: =Personnel!C58 -> 46023 | D41: =Personnel!D58 -> 46054 | E41: =Personnel!E58 -> 46082 | F41: =Personnel!F58 -> 46113 | G41: =Personnel!G58 -> 46143 | H41: =Personnel!H58 -> 46174 | I41: =Personnel!I58 -> 46204 | J41: =Personnel!J58 -> 46235 | ... N41: =Personnel!N58 -> 46357
B42: Cost Increase Coefficient | C42: 1 | D42: =C42 -> 1 | E42: =D42 -> 1 | F42: =E42 -> 1 | G42: =F42 -> 1 | H42: =G42 -> 1 | I42: =H42 -> 1 | J42: =I42 -> 1 | K42: =J42 -> 1 | ... N42: =M42 -> 1 | O42: Total
B43: =B10 -> Rent | C43: =C26*$C10*$D10 -> 59895 | D43: =D26*$C10*$D10*$D$42 -> 0 | E43: =E26*$C10*$D10*$D$42 -> 0 | F43: =F26*$C10*$D10*$D$42 -> 59895 | G43: =G26*$C10*$D10*$D$42 -> 0 | H43: =H26*$C10*$D10*$H$42 -> 0 | I43: =I26*$C10*$D10*$H$42 -> 59895 | J43: =J26*$C10*$D10*$H$42 -> 0 | K43: =K26*$C10*$D10*$H$42 -> 0 | L43: =L26*$C10*$D10*$L$42 -> 59895 | M43: =M26*$C10*$D10*$L$42 -> 0 | N43: =N26*$C10*$D10*$L$42 -> 0 | O43: =SUM(C43:N43) -> 239580
B44: =B11 -> Consumables | C44: =C27*$C11*$D11 -> 7935.9335 | D44: =D27*$C11*$D11*$D$42 -> 7935.9335 | E44: =E27*$C11*$D11*$D$42 -> 7935.9335 | F44: =F27*$C11*$D11*$D$42 -> 7935.9335 | G44: =G27*$C11*$D11*$D$42 -> 7935.9335 | H44: =H27*$C11*$D11*$H$42 -> 7935.9335 | I44: =I27*$C11*$D11*$H$42 -> 7935.9335 | J44: =J27*$C11*$D11*$H$42 -> 7935.9335 | K44: =K27*$C11*$D11*$H$42 -> 7935.9335 | L44: =L27*$C11*$D11*$L$42 -> 7935.9335 | M44: =M27*$C11*$D11*$L$42 -> 7935.9335 | N44: =N27*$C11*$D11*$L$42 -> 7935.9335 | O44: =SUM(C44:N44) -> 95231.202
B45: =B12 -> Office Supplies | C45: =C28*$C12*$D12*C42 -> 204.38 | D45: =D28*$C12*$D12*D42 -> 204.38 | E45: =E28*$C12*$D12*E42 -> 204.38 | F45: =F28*$C12*$D12*F42 -> 204.38 | G45: =G28*$C12*$D12*G42 -> 204.38 | H45: =H28*$C12*$D12*H42 -> 204.38 | I45: =I28*$C12*$D12*I42 -> 204.38 | J45: =J28*$C12*$D12*J42 -> 204.38 | ... N45: =N28*$C12*$D12*N42 -> 204.38 | O45: =SUM(C45:N45) -> 2452.56
B46: =B13 -> Services | C46: =C29*$C13*$D13 -> 794.2 | D46: =D29*$C13*$D13*$D$42 -> 794.2 | E46: =E29*$C13*$D13*$D$42 -> 794.2 | F46: =F29*$C13*$D13*$D$42 -> 794.2 | G46: =G29*$C13*$D13*$D$42 -> 794.2 | H46: =H29*$C13*$D13*$H$42 -> 794.2 | I46: =I29*$C13*$D13*$H$42 -> 794.2 | J46: =J29*$C13*$D13*$H$42 -> 794.2 | K46: =K29*$C13*$D13*$H$42 -> 794.2 | L46: =L29*$C13*$D13*$L$42 -> 794.2 | M46: =M29*$C13*$D13*$L$42 -> 794.2 | N46: =N29*$C13*$D13*$L$42 -> 794.2 | O46: =SUM(C46:N46) -> 9530.4
B47: =B14 -> Bills | C47: =C30*$C14*$D14 -> 660 | D47: =D30*$C14*$D14*$D$42 -> 660 | E47: =E30*$C14*$D14*$D$42 -> 660 | F47: =F30*$C14*$D14*$D$42 -> 660 | G47: =G30*$C14*$D14*$D$42 -> 660 | H47: =H30*$C14*$D14*$H$42 -> 660 | I47: =I30*$C14*$D14*$H$42 -> 660 | J47: =J30*$C14*$D14*$H$42 -> 660 | K47: =K30*$C14*$D14*$H$42 -> 660 | L47: =L30*$C14*$D14*$L$42 -> 660 | M47: =M30*$C14*$D14*$L$42 -> 660 | N47: =N30*$C14*$D14*$L$42 -> 660 | O47: =SUM(C47:N47) -> 7920
B48: =B15 -> Internet | C48: =C31*$C15*$D15 -> 2244.1738 | D48: =D31*$C15*$D15 -> 2244.1738 | E48: =E31*$C15*$D15 -> 2244.1738 | F48: =F31*$C15*$D15 -> 2244.1738 | G48: =G31*$C15*$D15 -> 2244.1738 | H48: =H31*$C15*$D15 -> 2244.1738 | I48: =I31*$C15*$D15 -> 2244.1738 | J48: =J31*$C15*$D15 -> 2244.1738 | ... N48: =N31*$C15*$D15 -> 2244.1738 | O48: =SUM(C48:N48) -> 26930.086
B49: =B16 -> Subscriptions | C49: =C32*$C16*$D16 -> 44287.868 | D49: =D32*$C16*$D16 -> 44287.868 | E49: =E32*$C16*$D16 -> 44287.868 | F49: =F32*$C16*$D16 -> 44287.868 | G49: =G32*$C16*$D16 -> 44287.868 | H49: =H32*$C16*$D16 -> 44287.868 | I49: =I32*$C16*$D16 -> 44287.868 | J49: =J32*$C16*$D16 -> 44287.868 | ... N49: =N32*$C16*$D16 -> 44287.868 | O49: =SUM(C49:N49) -> 531454.41
B50: =B17 -> Utilities | C50: =C33*$C17*$D17 -> 1935.1354 | D50: =D33*$C17*$D17 -> 1935.1354 | E50: =E33*$C17*$D17 -> 1935.1354 | F50: =F33*$C17*$D17 -> 1935.1354 | G50: =G33*$C17*$D17 -> 1935.1354 | H50: =H33*$C17*$D17 -> 1935.1354 | I50: =I33*$C17*$D17 -> 1935.1354 | J50: =J33*$C17*$D17 -> 1935.1354 | ... N50: =N33*$C17*$D17 -> 1935.1354 | O50: =SUM(C50:N50) -> 23221.625
B51: =B18 -> Transportation | C51: =C34*$C18*$D18 -> 525.03 | D51: =D34*$C18*$D18 -> 525.03 | E51: =E34*$C18*$D18 -> 525.03 | F51: =F34*$C18*$D18 -> 525.03 | G51: =G34*$C18*$D18 -> 525.03 | H51: =H34*$C18*$D18 -> 525.03 | I51: =I34*$C18*$D18 -> 525.03 | J51: =J34*$C18*$D18 -> 525.03 | ... N51: =N34*$C18*$D18 -> 525.03 | O51: =SUM(C51:N51) -> 6300.36
B52: =B19 -> Bank Charges | C52: =C35*$C19*$D19 -> 1710.3458 | D52: =D35*$C19*$D19 -> 1710.3458 | E52: =E35*$C19*$D19 -> 1710.3458 | F52: =F35*$C19*$D19 -> 1710.3458 | G52: =G35*$C19*$D19 -> 1710.3458 | H52: =H35*$C19*$D19 -> 1710.3458 | I52: =I35*$C19*$D19 -> 1710.3458 | J52: =J35*$C19*$D19 -> 1710.3458 | ... N52: =N35*$C19*$D19 -> 1710.3458 | O52: =SUM(C52:N52) -> 20524.15
B53: =B20 -> Marketing | C53: =C36*$C20*$D20 -> 0 | D53: =D36*$C20*$D20 -> 0 | E53: =E36*$C20*$D20 -> 0 | F53: =F36*$C20*$D20 -> 0 | G53: =G36*$C20*$D20 -> 0 | H53: =H36*$C20*$D20 -> 0 | I53: =I36*$C20*$D20 -> 0 | J53: =J36*$C20*$D20 -> 0 | ... N53: =N36*$C20*$D20 -> 0 | O53: =SUM(C53:N53) -> 0
B54: =B21 -> Medical | C54: =C37*$C21*$D21 -> 9776.8 | D54: =D37*$C21*$D21 -> 9776.8 | E54: =E37*$C21*$D21 -> 9776.8 | F54: =F37*$C21*$D21 -> 9776.8 | G54: =G37*$C21*$D21 -> 9776.8 | H54: =H37*$C21*$D21 -> 9776.8 | I54: =I37*$C21*$D21 -> 9776.8 | J54: =J37*$C21*$D21 -> 9776.8 | ... N54: =N37*$C21*$D21 -> 9776.8 | O54: =SUM(C54:N54) -> 117321.6
B55: =B22 -> Courses | C55: =C38*$C22*$D22 -> 0 | D55: =D38*$C22*$D22*$D$42 -> 0 | E55: =E38*$C22*$D22*$D$42 -> 0 | F55: =F38*$C22*$D22*$D$42 -> 0 | G55: =G38*$C22*$D22*$D$42 -> 0 | H55: =H38*$C22*$D22*$H$42 -> 0 | I55: =I38*$C22*$D22*$H$42 -> 0 | J55: =J38*$C22*$D22*$H$42 -> 0 | K55: =K38*$C22*$D22*$H$42 -> 0 | L55: =L38*$C22*$D22*$L$42 -> 0 | M55: =M38*$C22*$D22*$L$42 -> 0 | N55: =N38*$C22*$D22*$L$42 -> 0 | O55: =SUM(C55:N55) -> 0
B56: Total Other OPEX | C56: =SUM(C43:C55) -> 129968.87 | D56: =SUM(D43:D55) -> 70073.866 | E56: =SUM(E43:E55) -> 70073.866 | F56: =SUM(F43:F55) -> 129968.87 | G56: =SUM(G43:G55) -> 70073.866 | H56: =SUM(H43:H55) -> 70073.866 | I56: =SUM(I43:I55) -> 129968.87 | J56: =SUM(J43:J55) -> 70073.866 | ... N56: =SUM(N43:N55) -> 70073.866 | O56: =SUM(C56:N56) -> 1080466.4

Sheet Taxes
B2: Aura Systems
B3: Taxes Forecast
B4: Financial Numbers in 000s of EGP
B6: Inflation | C6: 0.15
B8: 2025 Monthly Salaries | C8: ='P&L'!F22/12 -> 400096.34
B9: 2025 Headcount | C9: 17
B10: 2025 Average Salary | C10: =C8/C9 -> 23535.079
B11: 2025 Monthly Payroll Tax | C11: =E21 -> 9618.9945
B12: 2025 Payroll Tax per employee | C12: =C11/C9 -> 565.82321
B13: 2026 Monthly Salaries | C13: =AVERAGE(Personnel!C152:N152)*1000 -> 521750
B14: 2026 Headcount | C14: 17
B15: 2026 Average Salary | C15: =C13/C14 -> 30691.176
B16: 2026 Salaries Increase | C16: 1.16
B18: Taxes Estimates
B19: Opex item | C19: Cost/Month | D19: Rep | E19: 2025
B20: =[11]Taxes!$B7 -> Deduction Tax | C20: =Result!I15*0 -> 0 | D20: 1 | E20: =AVERAGEA([12]Taxes!$C$7:$M$7) -> 16106.623
B21: =[11]Taxes!$B8 -> Payroll Tax | C21: =C12*C16*C14*1.1 -> 12273.837 | D21: 1 | E21: =AVERAGE([12]Taxes!$C$8:$M$8) -> 9618.9945
B22: =[11]Taxes!$B9 -> Income Tax | C22: =SUM(Result!H15*0.015)/12 -> 19250 | D22: 1 | E22: 0
B23: =[11]Taxes!$B11 -> Social Insurance | C23: =(35000*12+725000)/12 -> 95416.667 | D23: 1 | E23: =1250000/12 -> 104166.67
B25: Taxes Forecast
C26: =Personnel!C58 -> 46023 | D26: =Personnel!D58 -> 46054 | E26: =Personnel!E58 -> 46082 | F26: =Personnel!F58 -> 46113 | G26: =Personnel!G58 -> 46143 | H26: =Personnel!H58 -> 46174 | I26: =Personnel!I58 -> 46204 | J26: =Personnel!J58 -> 46235 | ... N26: =Personnel!N58 -> 46357
B27: =B20 -> Deduction Tax | C27: 1 | D27: 1 | E27: 1 | F27: 1 | G27: 1 | H27: 1 | I27: 1 | J27: 1 | K27: 1 | L27: 1 | M27: 1 | N27: 1
B28: =B21 -> Payroll Tax | C28: 1 | D28: 1 | E28: 1 | F28: 1 | G28: 1 | H28: 1 | I28: 1 | J28: 1 | K28: 1 | L28: 1 | M28: 1 | N28: 1
B29: =B22 -> Income Tax | C29: 1 | D29: 1 | E29: 1 | F29: 1 | G29: 1 | H29: 1 | I29: 1 | J29: 1 | K29: 1 | L29: 1 | M29: 1 | N29: 1
B30: =B23 -> Social Insurance | C30: 1 | D30: 1 | E30: 1 | F30: 1 | G30: 1 | H30: 1 | I30: 1 | J30: 1 | K30: 1 | L30: 1 | M30: 1 | N30: 1
B32: Taxes Expense
C33: =C26 -> 46023 | D33: =D26 -> 46054 | E33: =E26 -> 46082 | F33: =F26 -> 46113 | G33: =G26 -> 46143 | H33: =H26 -> 46174 | I33: =I26 -> 46204 | J33: =J26 -> 46235 | ... N33: =N26 -> 46357
B34: Cost Increase Coefficient | C34: 1 | D34: =C34 -> 1 | E34: =D34 -> 1 | F34: =E34 -> 1 | G34: =F34 -> 1 | H34: =G34 -> 1 | I34: =H34 -> 1 | J34: =I34 -> 1 | K34: =J34 -> 1 | ... N34: =M34 -> 1 | O34: Total
B35: =B20 -> Deduction Tax | C35: =C27*$C20*$D20 -> 0 | D35: =D27*$C20*$D20*$D$34 -> 0 | E35: =E27*$C20*$D20*$D$34 -> 0 | F35: =F27*$C20*$D20*$D$34 -> 0 | G35: =G27*$C20*$D20*$D$34 -> 0 | H35: =H27*$C20*$D20*$H$34 -> 0 | I35: =I27*$C20*$D20*$H$34 -> 0 | J35: =J27*$C20*$D20*$H$34 -> 0 | K35: =K27*$C20*$D20*$H$34 -> 0 | L35: =L27*$C20*$D20*$L$34 -> 0 | M35: =M27*$C20*$D20*$L$34 -> 0 | N35: =N27*$C20*$D20*$L$34 -> 0 | O35: =SUM(C35:N35) -> 0
B36: =B21 -> Payroll Tax | C36: =C28*$C21*$D21 -> 12273.837 | D36: =D28*$C21*$D21*$D$34 -> 12273.837 | E36: =E28*$C21*$D21*$D$34 -> 12273.837 | F36: =F28*$C21*$D21*$D$34 -> 12273.837 | G36: =G28*$C21*$D21*$D$34 -> 12273.837 | H36: =H28*$C21*$D21*$H$34 -> 12273.837 | I36: =I28*$C21*$D21*$H$34 -> 12273.837 | J36: =J28*$C21*$D21*$H$34 -> 12273.837 | K36: =K28*$C21*$D21*$H$34 -> 12273.837 | L36: =L28*$C21*$D21*$L$34 -> 12273.837 | M36: =M28*$C21*$D21*$L$34 -> 12273.837 | N36: =N28*$C21*$D21*$L$34 -> 12273.837 | O36: =SUM(C36:N36) -> 147286.04
B37: =B22 -> Income Tax | C37: =C29*$C22*$D22 -> 19250 | D37: =D29*$C22*$D22*$D$34 -> 19250 | E37: =E29*$C22*$D22 -> 19250 | F37: =F29*$C22*$D22 -> 19250 | G37: =G29*$C22*$D22 -> 19250 | H37: =H29*$C22*$D22 -> 19250 | I37: =I29*$C22*$D22 -> 19250 | J37: =J29*$C22*$D22 -> 19250 | K37: =K29*$C22*$D22 -> 19250 | L37: =L29*$C22*$D22 -> 19250 | ... N37: =N29*$C22*$D22 -> 19250 | O37: =SUM(C37:N37) -> 231000
B38: =B23 -> Social Insurance | C38: =C30*$C23*$D23 -> 95416.667 | D38: =D30*$C23*$D23*$D$34 -> 95416.667 | E38: =E30*$C23*$D23*$D$34 -> 95416.667 | F38: =F30*$C23*$D23*$D$34 -> 95416.667 | G38: =G30*$C23*$D23*$D$34 -> 95416.667 | H38: =H30*$C23*$D23*$H$34 -> 95416.667 | I38: =I30*$C23*$D23*$H$34 -> 95416.667 | J38: =J30*$C23*$D23*$H$34 -> 95416.667 | K38: =K30*$C23*$D23*$H$34 -> 95416.667 | L38: =L30*$C23*$D23*$L$34 -> 95416.667 | M38: =M30*$C23*$D23*$L$34 -> 95416.667 | N38: =N30*$C23*$D23*$L$34 -> 95416.667 | O38: =SUM(C38:N38) -> 1145000
B39: Total Other OPEX | C39: =SUM(C35:C38) -> 126940.5 | D39: =SUM(D35:D38) -> 126940.5 | E39: =SUM(E35:E38) -> 126940.5 | F39: =SUM(F35:F38) -> 126940.5 | G39: =SUM(G35:G38) -> 126940.5 | H39: =SUM(H35:H38) -> 126940.5 | I39: =SUM(I35:I38) -> 126940.5 | J39: =SUM(J35:J38) -> 126940.5 | ... N39: =SUM(N35:N38) -> 126940.5 | O39: =SUM(C39:N39) -> 1523286

Sheet P&L
B2: Aura Systems - Software Department
B3: P&L Budget
B4: Financial Numbers in EGP
B6: P&L | D6: 2026 | F6: 2025
B7: Item | C7: % | E7: %
B8: Revenue
B9: =Result!B7 -> Products | C9: =D9/D17 -> 0.16233766 | D9: =Result!H7 -> 2500000 | E9: =F9/$F$17 -> 0.17598812 | F9: =Growth!M7 -> 2140293.1
B10: =Result!B8 -> PHP | C10: =D10/$D$17 -> 0.31168831 | D10: =Result!H8 -> 4800000 | E10: =F10/$F$17 -> 0.30248736 | F10: =Growth!M8 -> 3678723.6
B11: .NET | C11: =D11/$D$17 -> 0.27272727 | D11: =Result!H9 -> 4200000 | E11: =F11/$F$17 -> 0.28898985 | F11: =Growth!M9 -> 3514572.5
B12: =Result!B10 -> Mobile Development | C12: =D12/$D$17 -> 0.12987013 | D12: =Result!H10 -> 2000000 | E12: =F12/$F$17 -> 0.11863489 | F12: =Growth!M10 -> 1442787.5
B13: =Result!B11 -> Support Contracts | C13: =D13/$D$17 -> 0 | D13: =Result!H11 -> 0 | E13: =F13/$F$17 -> 0 | F13: =Growth!M11 -> 0
B14: =Result!B12 -> Websites | C14: =D14/$D$17 -> 0.071428571 | D14: =Result!H12 -> 1100000 | E14: =F14/$F$17 -> 0.057089092 | F14: =Growth!M12 -> 694293.43
B15: Design | C15: =D15/$D$17 -> 0.027272727 | D15: =Result!H13 -> 420000 | E15: =F15/$F$17 -> 0.025825471 | F15: =Growth!M13 -> 314078.48
B16: =Result!B14 -> Hosting | C16: =D16/$D$17 -> 0.024675325 | D16: =Result!H14 -> 380000 | E16: =F16/$F$17 -> 0.030985223 | F16: =Growth!M14 -> 376829.19
B17: Total Sales | C17: =SUM(C9:C16) -> 1 | D17: =SUM(D9:D16) -> 15400000 | E17: =F17/$F$17 -> 1 | F17: =SUM(F9:F16) -> 12161578
B18: Cost of Sales | C18: 0.07 | D18: =C18*D17 -> 1078000 | E18: =F18/F17 -> 0.13640457 | F18: ='[13]I&E'!$AF$28/11*12 -> 1658894.8
B19: VAT | C19: 0.12 | D19: =D17*C19 -> 1848000 | E19: =F19/F17 -> 0.096535485 | F19: ='[13]I&E'!$AF$34/10*12 -> 1174023.8
B20: Gross Profit | C20: =D20/D17 -> 0.81 | D20: =D17-D18-D19 -> 12474000 | E20: =F20/F17 -> 0.76705994 | F20: =F17-F18-F19 -> 9328659.1
B21: Other Direct Expenses
B22: Salaries | C22: =D22/D20 -> 0.47190957 | D22: =Personnel!O152*1000-SUM(Personnel!C111:N111)*1000 -> 5886600 | E22: =F22/F20 -> 0.51466733 | F22: ='[12]Expenses 2k25'!$O$8/11*12 -> 4801156.1
B23: Sales Commissions | C23: =D23/D20 -> 0.0040083373 | D23: 50000 | E23: =F23/F20 -> 0 | F23: 0
B24: Earnings | C24: =D24/D20 -> 0.52408209 | D24: =D20-SUM(D22:D23) -> 6537400 | E24: =F24/F20 -> 0.48533267 | F24: =F20-SUM(F22:F23) -> 4527503.1
B25: Contribution
B26: G&A Salaries | C26: =D26/D20 -> 0.087734488 | D26: =Personnel!O117*1000 -> 1094400 | E26: =F26/F20 -> 0.090297525 | F26: =[14]Summary!$BD$23/11*12 -> 842354.83
B27: OpEx | C27: 0.08 | D27: =D17*C27 -> 1232000 | E27: 0.066 | F27: ='[12]Expenses 2k25'!$O$9 -> 864198.12
B28: Taxes | C28: =D28/D20 -> 0.12211689 | D28: =Taxes!O39 -> 1523286 | E28: =F28/F20 -> 0.19694395 | F28: ='[12]Expenses 2k25'!$O$13 -> 1837223
B29: Profit | C29: =D29/D20 -> 0.21546528 | D29: =D24-D26-D27-D28 -> 2687714 | E29: =F29/F20 -> 0.10545215 | F29: =F24-F26-F27-F28 -> 983727.14
B30: CapEx
B33: Sales Commissions
B34: Activity | C34: Percent
B35: =B9 -> Products | C35: 0.1
B36: =B10 -> PHP | C36: 0.03
B37: .Net | C37: 0
B38: =B12 -> Mobile Development | C38: 0.03
B39: =B13 -> Support Contracts | C39: 0.03
B40: =B14 -> Websites | C40: 0.06
B41: Design | C41: 0.06
B42: =B16 -> Hosting | C42: 0

Sheet CapEx
B2: Aura Systems
B3: CapEx Forecast
B4: Financial Numbers in EGP
B7: CapEx Estimates
B8: CapEx item | C8: Cost | D8: Rep
B9: Laptop | C9: 40000 | D9: 1
B10: SSD | C10: 2000 | D10: 1
B11: Nnetwork Booster | C11: 6000 | D11: 1
B12: Move | C12: 3000 | D12: 1
D13: 1
D14: 1
D15: 1
D16: 1
D17: 1
D18: 1
D19: 1
D20: 1
D21: 1
D22: 1
D23: 1
D24: 1
... D35: 1
B37: CapEx Forecast
C38: 46023 | D38: 46054 | E38: 46082 | F38: 46113 | G38: 46143 | H38: 46174 | I38: 46204 | J38: 46235 | K38: 46266 | L38: 46296 | M38: 46327 | N38: 46357
B39: Headcount | C39: ='[15]Personnel Forecast'!C106 -> 23.75 | D39: ='[15]Personnel Forecast'!D106 -> 26.75 | E39: ='[15]Personnel Forecast'!E106 -> 27.75 | F39: ='[15]Personnel Forecast'!F106 -> 28.75 | G39: ='[15]Personnel Forecast'!G106 -> 28.75 | H39: ='[15]Personnel Forecast'!H106 -> 29.75 | I39: ='[15]Personnel Forecast'!I106 -> 32.75 | J39: ='[15]Personnel Forecast'!J106 -> 32.75 | ... N39: ='[15]Personnel Forecast'!N106 -> 32.75
B40: =B9 -> Laptop
B41: =B10 -> SSD
B42: =B11 -> Nnetwork Booster
B43: =B12 -> Move
B44: =B13 -> 0
B45: =B14 -> 0
B46: =B15 -> 0
B47: =B16 -> 0
B48: =B17 -> 0
B49: =B18 -> 0
B50: =B19 -> 0
B51: =B20 -> 0
... B66: =B35 -> 0
B68: CapEx Forecast
C69: =C38 -> 46023 | D69: =D38 -> 46054 | E69: =E38 -> 46082 | F69: =F38 -> 46113 | G69: =G38 -> 46143 | H69: =H38 -> 46174 | I69: =I38 -> 46204 | J69: =J38 -> 46235 | ... N69: =N38 -> 46357
B70: Cost Increase Coefficient | C70: 1 | D70: =C70 -> 1 | E70: =D70 -> 1 | F70: =E70 -> 1 | G70: =F70 -> 1 | H70: =G70 -> 1 | I70: =H70 -> 1 | J70: =I70 -> 1 | K70: =J70 -> 1 | ... N70: =M70 -> 1
B71: =B9 -> Laptop | C71: =C40*$C9*$D9 -> 0 | D71: =D40*$C9*$D9 -> 0 | E71: =E40*$C9*$D9 -> 0 | F71: =F40*$C9*$D9 -> 0 | G71: =G40*$C9*$D9 -> 0 | H71: =H40*$C9*$D9 -> 0 | I71: =I40*$C9*$D9 -> 0 | J71: =J40*$C9*$D9 -> 0 | ... N71: =N40*$C9*$D9 -> 0
B72: =B10 -> SSD | D72: =D41*$C10*$D10 -> 0 | E72: =E41*$C10*$D10 -> 0 | F72: =F41*$C10*$D10 -> 0 | G72: =G41*$C10*$D10 -> 0 | H72: =H41*$C10*$D10 -> 0 | I72: =I41*$C10*$D10 -> 0 | J72: =J41*$C10*$D10 -> 0 | K72: =K41*$C10*$D10 -> 0 | ... N72: =N41*$C10*$D10 -> 0
B73: =B11 -> Nnetwork Booster | C73: =C42*$C11*$D11 -> 0 | D73: =D42*$C11*$D11 -> 0 | E73: =E42*$C11*$D11 -> 0 | F73: =F42*$C11*$D11 -> 0 | G73: =G42*$C11*$D11 -> 0 | H73: =H42*$C11*$D11 -> 0 | I73: =I42*$C11*$D11 -> 0 | J73: =J42*$C11*$D11 -> 0 | ... N73: =N42*$C11*$D11 -> 0
B74: =B12 -> Move | C74: =C43*$C12*$D12 -> 0 | D74: =D43*$C12*$D12 -> 0 | E74: =E43*$C12*$D12 -> 0 | F74: =F43*$C12*$D12 -> 0 | G74: =G43*$C12*$D12 -> 0 | H74: =H43*$C12*$D12 -> 0 | I74: =I43*$C12*$D12 -> 0 | J74: =J43*$C12*$D12 -> 0 | ... N74: =N43*$C12*$D12 -> 0
B75: =B13 -> 0 | C75: =C44*$C13*$D13 -> 0 | D75: =D44*$C13*$D13 -> 0 | E75: =E44*$C13*$D13 -> 0 | F75: =F44*$C13*$D13 -> 0 | G75: =G44*$C13*$D13 -> 0 | H75: =H44*$C13*$D13 -> 0 | I75: =I44*$C13*$D13 -> 0 | J75: =J44*$C13*$D13 -> 0 | ... N75: =N44*$C13*$D13 -> 0
B76: =B14 -> 0 | C76: =C45*$C14*$D14 -> 0 | D76: =D45*$C14*$D14 -> 0 | E76: =E45*$C14*$D14 -> 0 | F76: =F45*$C14*$D14 -> 0 | G76: =G45*$C14*$D14 -> 0 | H76: =H45*$C14*$D14 -> 0 | I76: =I45*$C14*$D14 -> 0 | J76: =J45*$C14*$D14 -> 0 | ... N76: =N45*$C14*$D14 -> 0
B77: =B15 -> 0 | C77: =C46*$C15*$D15 -> 0 | D77: =D46*$C15*$D15 -> 0 | E77: =E46*$C15*$D15 -> 0 | F77: =F46*$C15*$D15 -> 0 | G77: =G46*$C15*$D15 -> 0 | H77: =H46*$C15*$D15 -> 0 | I77: =I46*$C15*$D15 -> 0 | J77: =J46*$C15*$D15 -> 0 | ... N77: =N46*$C15*$D15 -> 0
B78: =B16 -> 0 | C78: =C47*$C16*$D16 -> 0 | D78: =D47*$C16*$D16 -> 0 | E78: =E47*$C16*$D16 -> 0 | F78: =F47*$C16*$D16 -> 0 | G78: =G47*$C16*$D16 -> 0 | H78: =H47*$C16*$D16 -> 0 | I78: =I47*$C16*$D16 -> 0 | J78: =J47*$C16*$D16 -> 0 | ... N78: =N47*$C16*$D16 -> 0
B79: =B17 -> 0 | C79: =C48*$C17*$D17 -> 0 | D79: =D48*$C17*$D17 -> 0 | E79: =E48*$C17*$D17 -> 0 | F79: =F48*$C17*$D17 -> 0 | G79: =G48*$C17*$D17 -> 0 | H79: =H48*$C17*$D17 -> 0 | I79: =I48*$C17*$D17 -> 0 | J79: =J48*$C17*$D17 -> 0 | ... N79: =N48*$C17*$D17 -> 0
B80: =B18 -> 0 | C80: =C49*$C18*$D18 -> 0 | D80: =D49*$C18*$D18 -> 0 | E80: =E49*$C18*$D18 -> 0 | F80: =F49*$C18*$D18 -> 0 | G80: =G49*$C18*$D18 -> 0 | H80: =H49*$C18*$D18 -> 0 | I80: =I49*$C18*$D18 -> 0 | J80: =J49*$C18*$D18 -> 0 | ... N80: =N49*$C18*$D18 -> 0
B81: =B19 -> 0 | C81: =C50*$C19*$D19 -> 0 | D81: =D50*$C19*$D19 -> 0 | E81: =E50*$C19*$D19 -> 0 | F81: =F50*$C19*$D19 -> 0 | G81: =G50*$C19*$D19 -> 0 | H81: =H50*$C19*$D19 -> 0 | I81: =I50*$C19*$D19 -> 0 | J81: =J50*$C19*$D19 -> 0 | ... N81: =N50*$C19*$D19 -> 0
B82: =B20 -> 0 | C82: =C51*$C20*$D20 -> 0 | D82: =D51*$C20*$D20 -> 0 | E82: =E51*$C20*$D20 -> 0 | F82: =F51*$C20*$D20 -> 0 | G82: =G51*$C20*$D20 -> 0 | H82: =H51*$C20*$D20 -> 0 | I82: =I51*$C20*$D20 -> 0 | J82: =J51*$C20*$D20 -> 0 | ... N82: =N51*$C20*$D20 -> 0
B83: =B21 -> 0 | C83: =C52*$C21*$D21 -> 0 | D83: =D52*$C21*$D21 -> 0 | E83: =E52*$C21*$D21 -> 0 | F83: =F52*$C21*$D21 -> 0 | G83: =G52*$C21*$D21 -> 0 | H83: =H52*$C21*$D21 -> 0 | I83: =I52*$C21*$D21 -> 0 | J83: =J52*$C21*$D21 -> 0 | ... N83: =N52*$C21*$D21 -> 0
B84: =B22 -> 0
B85: =B23 -> 0 | C85: =C54*$C23*$D23 -> 0 | D85: =D54*$C23*$D23 -> 0 | E85: =E54*$C23*$D23 -> 0 | F85: =F54*$C23*$D23 -> 0 | G85: =G54*$C23*$D23 -> 0 | H85: =H54*$C23*$D23 -> 0 | I85: =I54*$C23*$D23 -> 0 | J85: =J54*$C23*$D23 -> 0 | ... N85: =N54*$C23*$D23 -> 0
B86: =B24 -> 0 | C86: =C55*$C24*$D24 -> 0 | D86: =D55*$C24*$D24 -> 0 | E86: =E55*$C24*$D24 -> 0 | F86: =F55*$C24*$D24 -> 0 | G86: =G55*$C24*$D24 -> 0 | H86: =H55*$C24*$D24 -> 0 | I86: =I55*$C24*$D24 -> 0 | J86: =J55*$C24*$D24 -> 0 | ... N86: =N55*$C24*$D24 -> 0
B87: =B25 -> 0 | C87: =C56*$C25*$D25 -> 0 | D87: =D56*$C25*$D25 -> 0 | E87: =E56*$C25*$D25 -> 0 | F87: =F56*$C25*$D25 -> 0 | G87: =G56*$C25*$D25 -> 0 | H87: =H56*$C25*$D25 -> 0 | I87: =I56*$C25*$D25 -> 0 | J87: =J56*$C25*$D25 -> 0 | ... N87: =N56*$C25*$D25 -> 0
B88: =B26 -> 0 | C88: =C57*$C26*$D26 -> 0 | D88: =D57*$C26*$D26 -> 0 | E88: =E57*$C26*$D26 -> 0 | F88: =F57*$C26*$D26 -> 0 | G88: =G57*$C26*$D26 -> 0 | H88: =H57*$C26*$D26 -> 0 | I88: =I57*$C26*$D26 -> 0 | J88: =J57*$C26*$D26 -> 0 | ... N88: =N57*$C26*$D26 -> 0
B89: =B27 -> 0 | C89: =C58*$C27*$D27 -> 0 | D89: =D58*$C27*$D27 -> 0 | E89: =E58*$C27*$D27 -> 0 | F89: =F58*$C27*$D27 -> 0 | G89: =G58*$C27*$D27 -> 0 | H89: =H58*$C27*$D27 -> 0 | I89: =I58*$C27*$D27 -> 0 | J89: =J58*$C27*$D27 -> 0 | ... N89: =N58*$C27*$D27 -> 0
B90: =B28 -> 0 | C90: =C59*$C28*$D28 -> 0 | D90: =D59*$C28*$D28 -> 0 | E90: =E59*$C28*$D28 -> 0 | F90: =F59*$C28*$D28 -> 0 | G90: =G59*$C28*$D28 -> 0 | H90: =H59*$C28*$D28 -> 0 | I90: =I59*$C28*$D28 -> 0 | J90: =J59*$C28*$D28 -> 0 | ... N90: =N59*$C28*$D28 -> 0
B91: =B29 -> 0 | C91: =C60*$C29*$D29 -> 0 | D91: =D60*$C29*$D29 -> 0 | E91: =E60*$C29*$D29 -> 0 | F91: =F60*$C29*$D29 -> 0 | G91: =G60*$C29*$D29 -> 0 | H91: =H60*$C29*$D29 -> 0 | I91: =I60*$C29*$D29 -> 0 | J91: =J60*$C29*$D29 -> 0 | ... N91: =N60*$C29*$D29 -> 0
B92: =B30 -> 0 | C92: =C61*$C30*$D30 -> 0 | D92: =D61*$C30*$D30 -> 0 | E92: =E61*$C30*$D30 -> 0 | F92: =F61*$C30*$D30 -> 0 | G92: =G61*$C30*$D30 -> 0 | H92: =H61*$C30*$D30 -> 0 | I92: =I61*$C30*$D30 -> 0 | J92: =J61*$C30*$D30 -> 0 | ... N92: =N61*$C30*$D30 -> 0
B93: =B31 -> 0 | C93: =C62*$C31*$D31 -> 0 | D93: =D62*$C31*$D31 -> 0 | E93: =E62*$C31*$D31 -> 0 | F93: =F62*$C31*$D31 -> 0 | G93: =G62*$C31*$D31 -> 0 | H93: =H62*$C31*$D31 -> 0 | I93: =I62*$C31*$D31 -> 0 | J93: =J62*$C31*$D31 -> 0 | ... N93: =N62*$C31*$D31 -> 0
B94: =B32 -> 0 | C94: =C63*$C32*$D32 -> 0 | D94: =D63*$C32*$D32 -> 0 | E94: =E63*$C32*$D32 -> 0 | F94: =F63*$C32*$D32 -> 0 | G94: =G63*$C32*$D32 -> 0 | H94: =H63*$C32*$D32 -> 0 | I94: =I63*$C32*$D32 -> 0 | J94: =J63*$C32*$D32 -> 0 | ... N94: =N63*$C32*$D32 -> 0
B95: =B33 -> 0 | C95: =C64*$C33*$D33 -> 0 | D95: =D64*$C33*$D33 -> 0 | E95: =E64*$C33*$D33 -> 0 | F95: =F64*$C33*$D33 -> 0 | G95: =G64*$C33*$D33 -> 0 | H95: =H64*$C33*$D33 -> 0 | I95: =I64*$C33*$D33 -> 0 | J95: =J64*$C33*$D33 -> 0 | ... N95: =N64*$C33*$D33 -> 0
B96: =B34 -> 0 | C96: =C65*$C34*$D34 -> 0 | D96: =D65*$C34*$D34 -> 0 | E96: =E65*$C34*$D34 -> 0 | F96: =F65*$C34*$D34 -> 0 | G96: =G65*$C34*$D34 -> 0 | H96: =H65*$C34*$D34 -> 0 | I96: =I65*$C34*$D34 -> 0 | J96: =J65*$C34*$D34 -> 0 | ... N96: =N65*$C34*$D34 -> 0
B97: =B35 -> 0 | C97: =C66*$C35*$D35 -> 0 | D97: =D66*$C35*$D35 -> 0 | E97: =E66*$C35*$D35 -> 0 | F97: =F66*$C35*$D35 -> 0 | G97: =G66*$C35*$D35 -> 0 | H97: =H66*$C35*$D35 -> 0 | I97: =I66*$C35*$D35 -> 0 | J97: =J66*$C35*$D35 -> 0 | ... N97: =N66*$C35*$D35 -> 0
B98: Total CapEx | C98: =SUM(C71:C97) -> 0 | D98: =SUM(D71:D97) -> 0 | E98: =SUM(E71:E97) -> 0 | F98: =SUM(F71:F97) -> 0 | G98: =SUM(G71:G97) -> 0 | H98: =SUM(H71:H97) -> 0 | I98: =SUM(I71:I97) -> 0 | J98: =SUM(J71:J97) -> 0 | ... N98: =SUM(N71:N97) -> 0 | O98: =AVERAGE(C98:N98) -> 0
